Workbook

Sheet README
A1: ⚠ SIMULATED FINANCIAL INFORMATION - synthetic demonstration accounts of a fictional auto care group, not actual company records. Synthetic data generated for a VisiVault Analytics proof of concept (seed 20240103). Fictional auto care group.
A2: Prairie Auto Care Group (fictional) - Integrated Three-Statement Financial Model
A3: Developed by VisiVault Analytics Ltd. | October 2026
A5: WHAT THIS IS
A6: SIMULATED accounts of a FICTIONAL multi-location Calgary collision & car care group, built by double entry from synthetic operational data.
A7: Synthetic demonstration data. Not actual Ultimate Car Care Group records. Jan-2024 to Sep-2026 are simulated actuals; Oct-2026 to Sep-2027 are FORECASTS.
A9: HOW TO USE
A10: 1. Assumptions!C4 - choose Conservative / Base / Optimistic / Custom (edit the Custom column freely: efficiency, parts cost, cycle time, volume, margin,
A11: collection delays, extra technicians, service-line expansion, opex, prime rate).
A12: 2. Drivers - edit any blue monthly input (demand and technician capacity in billed hours, staffing plan, leases, opex, capex, loan schedule).
A13: 3. Forecast - three statements recalculate; the CHECKS rows and the Checks sheet must stay at 0 / TRUE.
A14: 4. Scenario_Results - stored comparison of the three scenarios and the sensitivity cases.
... A30: Assumptions | Drivers | Forecast | Scenario_Results | Checks | Hist_IS | Hist_BS | Hist_CF | Hist_Balances

Sheet Assumptions
A1: ⚠ SIMULATED FINANCIAL INFORMATION - synthetic demonstration accounts of a fictional auto care group, not actual company records. Synthetic data generated for a VisiVault Analytics proof of concept (seed 20240103). Fictional auto care group.
A2: Forecast assumptions - choose a scenario, or edit the Custom column
A3: Blue cells on yellow are inputs. Column H (Active) feeds every forecast formula.
B4: Active scenario >> | C4: Base
A7: Key | B7: Scenario driver | C7: Unit | D7: Conservative | E7: Base | F7: Optimistic | G7: Custom | H7: Active
A8: eff_change | B8: Technician efficiency change | C8: % | D8: -0.03 | E8: 0 | F8: 0.05 | G8: 0 | H8: =INDEX(D8:G8,MATCH($C$4,$D$7:$G$7,0)) -> 0
A9: parts_cost_change | B9: Parts procurement cost change | C9: % | D9: 0.03 | E9: 0 | F9: -0.02 | G9: 0 | H9: =INDEX(D9:G9,MATCH($C$4,$D$7:$G$7,0)) -> 0
A10: cycle_change | B10: Repair cycle-time change | C10: % | D10: 0 | E10: 0 | F10: -0.1 | G10: 0 | H10: =INDEX(D10:G10,MATCH($C$4,$D$7:$G$7,0)) -> 0
A11: appt_change | B11: Appointment volume change | C11: % | D11: -0.06 | E11: 0 | F11: 0.05 | G11: 0 | H11: =INDEX(D11:G11,MATCH($C$4,$D$7:$G$7,0)) -> 0
A12: margin_change | B12: Gross-margin improvement (relative) | C12: % | D12: 0 | E12: 0 | F12: 0 | G12: 0 | H12: =INDEX(D12:G12,MATCH($C$4,$D$7:$G$7,0)) -> 0
A13: collect_change | B13: Receivable collection-delay change | C13: % | D13: 0.15 | E13: 0 | F13: -0.1 | G13: 0 | H13: =INDEX(D13:G13,MATCH($C$4,$D$7:$G$7,0)) -> 0
A14: hires | B14: Additional collision technicians (from Dec-2026) | C14: # | D14: 0 | E14: 0 | F14: 0 | G14: 0 | H14: =INDEX(D14:G14,MATCH($C$4,$D$7:$G$7,0)) -> 0
A15: expansion | B15: Detailing & paint-protection expansion | C15: % | D15: 0 | E15: 0 | F15: 0.1 | G15: 0 | H15: =INDEX(D15:G15,MATCH($C$4,$D$7:$G$7,0)) -> 0
A16: opex_change | B16: Controllable operating-expense change | C16: % | D16: 0.02 | E16: 0 | F16: 0 | G16: 0 | H16: =INDEX(D16:G16,MATCH($C$4,$D$7:$G$7,0)) -> 0
A17: rate_change | B17: Prime-rate change | C17: % | D17: 0.005 | E17: 0 | F17: 0 | G17: 0 | H17: =INDEX(D17:G17,MATCH($C$4,$D$7:$G$7,0)) -> 0
B19: Scenario notes
B20: Conservative | C20: Demand -6%, technician efficiency -3%, parts cost +3%, collections 15% slower, opex +2%, prime +50 bps.
B21: Base | C21: Model forecasts of demand and technician capacity, TTM rates and cost ratios, current staffing plan and leases, prime flat.
B22: Optimistic | C22: Demand +5%, efficiency +5%, parts cost -2%, cycle time -10%, collections 10% faster, detailing & protection +10%.
A24: Key | B24: Calibrated / policy parameter (TTM Oct-2025 to Sep-2026 unless stated) | H24: Value
A25: rph_coll | B25: Collision revenue per billed body & paint hour (incl. parts, materials, sublet) | H25: 348.97632
A26: rph_mech | B26: Mechanical revenue per billed mechanical hour | H26: 376.78664
A27: parts_coll | B27: Parts cost / collision revenue | H27: 0.39767955
A28: parts_mech | B28: Parts cost / mechanical revenue | H28: 0.34233577
A29: parts_oth | B29: Parts cost / detailing, glass & other revenue | H29: 0.20953297
A30: mat_coll | B30: Paint & materials cost / collision revenue | H30: 0.035391845
A31: mat_oth | B31: Materials cost / detailing & other revenue | H31: 0.042028689
A32: sublet_coll | B32: Sublet cost / collision revenue | H32: 0.014779682
A33: sublet_mech | B33: Sublet cost / mechanical revenue | H33: 0.012420553
A34: adj_rate | B34: Discounts, short-pays & adjustments / service revenue | H34: 0.0073502577
A35: warranty_ratio | B35: Warranty rework parts & sublet / net revenue | H35: 0.00089998412
A36: eff_coll_ttm | B36: eff_coll_ttm | H36: 1.1369002
... A69: sbd_limit | B69: Small-business limit | H69: 500000

Sheet Drivers
A1: ⚠ SIMULATED FINANCIAL INFORMATION - synthetic demonstration accounts of a fictional auto care group, not actual company records. Synthetic data generated for a VisiVault Analytics proof of concept (seed 20240103). Fictional auto care group.
A2: Monthly drivers (inputs) - demand & capacity from the predictive models, staffing plan, leases, opex plan, capex plan, loan schedule
A3: Edit any blue cell; the forecast recalculates. Column C = actual 30-Sep-2026 position (not used by drivers).
A5: Key | B5: Line | C5: Sep-2026 actual | D5: Oct-2026 | E5: Nov-2026 | F5: Dec-2026 | G5: Jan-2027 | H5: Feb-2027 | I5: Mar-2027 | J5: Apr-2027 | K5: May-2027 | L5: Jun-2027 | M5: Jul-2027 | N5: Aug-2027 | O5: Sep-2027 | P5: 12-month total
A6: dem_coll_base | B6: Collision demand - billed body & paint hours (Model 2 RO-volume forecast x hours per RO) | D6: 2285.6 | E6: 2714 | F6: 2288.9 | G6: 2199.2 | H6: 2254.1 | I6: 2082 | J6: 2057.9 | K6: 1678.7 | L6: 2059.2 | M6: 1983.4 | N6: 2130.1 | O6: 1718
A7: dem_mech_base | B7: Mechanical demand - billed hours (Model 2) | D7: 1278.0768 | E7: 1093.5014 | F7: 640.81542 | G7: 770.30167 | H7: 759.74213 | I7: 719.22129 | J7: 955.6846 | K7: 1092.5229 | L7: 780.84289 | M7: 700.79849 | N7: 700.32618 | O7: 733.43261
A8: cap_coll_base | B8: Collision technician capacity - billed hours (Model 5 x efficiency) | D8: 2713.7915 | E8: 2648.6804 | F8: 2372.2778 | G8: 2621.7278 | H8: 2478.8523 | I8: 2836.5126 | J8: 2912.53 | K8: 2601.6664 | L8: 2836.811 | M8: 2289.0523 | N8: 2475.4212 | O8: 2756.6342
A9: cap_mech_base | B9: Mechanical technician capacity - billed hours (Model 5 x efficiency) | D9: 1408.5736 | E9: 1361.8048 | F9: 1260.7605 | G9: 1366.2447 | H9: 1300.8407 | I9: 1467.7622 | J9: 1511.0391 | K9: 1343.141 | L9: 1472.8829 | M9: 1129.4398 | N9: 1315.9957 | O9: 1429.8814
A10: rev_detail_base | B10: Detailing revenue (Model 1) | D10: 49818.876 | E10: 28914.678 | F10: 28623.463 | G10: 31386.088 | H10: 26212.376 | I10: 42310.946 | J10: 60392.943 | K10: 65411.937 | L10: 72507.922 | M10: 59629.453 | N10: 62989.913 | O10: 53724.191
A11: rev_glass_base | B11: Glass revenue (Model 1) | D11: 53335.919 | E11: 50974.559 | F11: 36004.832 | G11: 52279.429 | H11: 46466.136 | I11: 68420.978 | J11: 69253.866 | K11: 76289.37 | L11: 61685.239 | M11: 56157.116 | N11: 73282.19 | O11: 47150.977
A12: rev_other_base | B12: Other services revenue (Model 1) | D12: 44844.94 | E12: 38056.74 | F12: 22726.79 | G12: 46911.53 | H12: 29218.25 | I12: 62981.53 | J12: 77274.89 | K12: 54051.37 | L12: 86525.79 | M12: 141310.65 | N12: 74340.63 | O12: 90328.55
A13: payroll_tech_base | B13: Technician payroll - staffing plan, regular & paid-absence hours (TTM same month +3%) | D13: 257413.38 | E13: 223478.67 | F13: 257413.38 | G13: 265534.83 | H13: 244269.22 | I13: 282315.27 | J13: 269633.25 | K13: 257892.31 | L13: 290733.37 | M13: 290733.37 | N13: 278383.11 | O13: 277668.71
A14: staff_d | B14: Staff compensation plan | D14: 141220.64 | E14: 141220.64 | F14: 141220.64 | G14: 145457.26 | H14: 145457.26 | I14: 145457.26 | J14: 145457.26 | K14: 145457.26 | L14: 145457.26 | M14: 145457.26 | N14: 145457.26 | O14: 145457.26
A15: occupancy_d | B15: Occupancy: lease schedule (+3% Jan) + utilities seasonal | D15: 99702.616 | E15: 104967.14 | F15: 105416.81 | G15: 108921.59 | H15: 108259.45 | I15: 108749.05 | J15: 102371.76 | K15: 102558.95 | L15: 102699.74 | M15: 102658.64 | N15: 102532.77 | O15: 102666.49
A16: marketing_d | B16: Marketing plan | D16: 10799.995 | E16: 10686.671 | F16: 10359.285 | G16: 9703.962 | H16: 10590.864 | I16: 9425.0902 | J16: 9514.583 | K16: 9872.882 | L16: 11208.488 | M16: 10787.961 | N16: 9762.9507 | O16: 9637.7162
A17: ga_d | B17: General & administrative | D17: 30221.992 | E17: 30354.647 | F17: 29455.302 | G17: 34314.663 | H17: 30551.427 | I17: 31001.279 | J17: 31503.816 | K17: 30906.815 | L17: 31134.754 | M17: 30587.087 | N17: 31276.491 | O17: 30287.151
... A30: q_start | B30: Flag: first month of quarter | D30: 1 | E30: 0 | F30: 0 | G30: 1 | H30: 0 | I30: 0 | J30: 1 | K30: 0 | L30: 0 | M30: 1 | N30: 0 | O30: 0

Sheet Forecast
A1: ⚠ SIMULATED FINANCIAL INFORMATION - synthetic demonstration accounts of a fictional auto care group, not actual company records. Synthetic data generated for a VisiVault Analytics proof of concept (seed 20240103). Fictional auto care group.
A2: Integrated 12-month forecast Oct-2026 to Sep-2027 (FORECAST - not historical fact)
A3: Every cell in columns D:O is a formula driven by Assumptions (active scenario) and Drivers. Column C links to the historical ledger.
A5: Key | B5: Line | C5: Sep-2026 actual | D5: Oct-2026 | E5: Nov-2026 | F5: Dec-2026 | G5: Jan-2027 | H5: Feb-2027 | I5: Mar-2027 | J5: Apr-2027 | K5: May-2027 | L5: Jun-2027 | M5: Jul-2027 | N5: Aug-2027 | O5: Sep-2027 | P5: 12-month total
A7: INCOME STATEMENT (forecast)
A8: rev_collision | B8: Collision repair revenue | D8: =D93*Assumptions!$H$25 -> 1041753.9 | E8: =E93*Assumptions!$H$25 -> 1016759.4 | F8: =F93*Assumptions!$H$25 -> 856631.52 | G8: =G93*Assumptions!$H$25 -> 767468.73 | H8: =H93*Assumptions!$H$25 -> 786627.53 | I8: =I93*Assumptions!$H$25 -> 726568.7 | J8: =J93*Assumptions!$H$25 -> 718158.37 | K8: =K93*Assumptions!$H$25 -> 585826.55 | ... O8: =O93*Assumptions!$H$25 -> 599541.32 | P8: =SUM(D8:O8) -> 9253462.1
A9: rev_mech | B9: Mechanical service revenue | D9: =D100*Assumptions!$H$26 -> 517506.29 | E9: =E100*Assumptions!$H$26 -> 412016.71 | F9: =F100*Assumptions!$H$26 -> 241450.68 | G9: =G100*Assumptions!$H$26 -> 290239.38 | H9: =H100*Assumptions!$H$26 -> 286260.68 | I9: =I100*Assumptions!$H$26 -> 270992.97 | J9: =J100*Assumptions!$H$26 -> 360089.19 | K9: =K100*Assumptions!$H$26 -> 411648.02 | ... O9: =O100*Assumptions!$H$26 -> 276347.61 | P9: =SUM(D9:O9) -> 3888687.7
A10: rev_detail | B10: Detailing revenue | D10: =Drivers!D10*(1+Assumptions!$H$11)*(1+Assumptions!$H$15) -> 49818.876 | E10: =Drivers!E10*(1+Assumptions!$H$11)*(1+Assumptions!$H$15) -> 28914.678 | F10: =Drivers!F10*(1+Assumptions!$H$11)*(1+Assumptions!$H$15) -> 28623.463 | G10: =Drivers!G10*(1+Assumptions!$H$11)*(1+Assumptions!$H$15) -> 31386.088 | H10: =Drivers!H10*(1+Assumptions!$H$11)*(1+Assumptions!$H$15) -> 26212.376 | I10: =Drivers!I10*(1+Assumptions!$H$11)*(1+Assumptions!$H$15) -> 42310.946 | J10: =Drivers!J10*(1+Assumptions!$H$11)*(1+Assumptions!$H$15) -> 60392.943 | K10: =Drivers!K10*(1+Assumptions!$H$11)*(1+Assumptions!$H$15) -> 65411.937 | ... O10: =Drivers!O10*(1+Assumptions!$H$11)*(1+Assumptions!$H$15) -> 53724.191 | P10: =SUM(D10:O10) -> 581922.79
A11: rev_glass | B11: Glass repair revenue | D11: =Drivers!D11*(1+Assumptions!$H$11) -> 53335.919 | E11: =Drivers!E11*(1+Assumptions!$H$11) -> 50974.559 | F11: =Drivers!F11*(1+Assumptions!$H$11) -> 36004.832 | G11: =Drivers!G11*(1+Assumptions!$H$11) -> 52279.429 | H11: =Drivers!H11*(1+Assumptions!$H$11) -> 46466.136 | I11: =Drivers!I11*(1+Assumptions!$H$11) -> 68420.978 | J11: =Drivers!J11*(1+Assumptions!$H$11) -> 69253.866 | K11: =Drivers!K11*(1+Assumptions!$H$11) -> 76289.37 | ... O11: =Drivers!O11*(1+Assumptions!$H$11) -> 47150.977 | P11: =SUM(D11:O11) -> 691300.61
A12: rev_other | B12: Other service revenue (PDR, paint protection, ADAS, fees) | D12: =Drivers!D12*(1+Assumptions!$H$11)*(1+Assumptions!$H$15) -> 44844.94 | E12: =Drivers!E12*(1+Assumptions!$H$11)*(1+Assumptions!$H$15) -> 38056.74 | F12: =Drivers!F12*(1+Assumptions!$H$11)*(1+Assumptions!$H$15) -> 22726.79 | G12: =Drivers!G12*(1+Assumptions!$H$11)*(1+Assumptions!$H$15) -> 46911.53 | H12: =Drivers!H12*(1+Assumptions!$H$11)*(1+Assumptions!$H$15) -> 29218.25 | I12: =Drivers!I12*(1+Assumptions!$H$11)*(1+Assumptions!$H$15) -> 62981.53 | J12: =Drivers!J12*(1+Assumptions!$H$11)*(1+Assumptions!$H$15) -> 77274.89 | K12: =Drivers!K12*(1+Assumptions!$H$11)*(1+Assumptions!$H$15) -> 54051.37 | ... O12: =Drivers!O12*(1+Assumptions!$H$11)*(1+Assumptions!$H$15) -> 90328.55 | P12: =SUM(D12:O12) -> 768571.66
A13: gross_rev | B13: Service revenue | D13: =D8+D9+D10+D11+D12 -> 1707259.9 | E13: =E8+E9+E10+E11+E12 -> 1546722.1 | F13: =F8+F9+F10+F11+F12 -> 1185437.3 | G13: =G8+G9+G10+G11+G12 -> 1188285.1 | H13: =H8+H9+H10+H11+H12 -> 1174785 | I13: =I8+I9+I10+I11+I12 -> 1171275.1 | J13: =J8+J9+J10+J11+J12 -> 1285169.3 | K13: =K8+K9+K10+K11+K12 -> 1193227.2 | ... O13: =O8+O9+O10+O11+O12 -> 1067092.6 | P13: =SUM(D13:O13) -> 15183945
A14: adjustments | B14: Less: discounts, insurer short-pays & adjustments | D14: =-Assumptions!$H$34*D13 -> -12548.8 | E14: =-Assumptions!$H$34*E13 -> -11368.806 | F14: =-Assumptions!$H$34*F13 -> -8713.2696 | G14: =-Assumptions!$H$34*G13 -> -8734.2021 | H14: =-Assumptions!$H$34*H13 -> -8634.9723 | I14: =-Assumptions!$H$34*I13 -> -8609.174 | J14: =-Assumptions!$H$34*J13 -> -9446.3252 | K14: =-Assumptions!$H$34*K13 -> -8770.5277 | ... O14: =-Assumptions!$H$34*O13 -> -7843.4059 | P14: =SUM(D14:O14) -> -111605.91
A15: net_rev | B15: Total net revenue | D15: =D13+D14 -> 1694711.1 | E15: =E13+E14 -> 1535353.3 | F15: =F13+F14 -> 1176724 | G15: =G13+G14 -> 1179550.9 | H15: =H13+H14 -> 1166150 | I15: =I13+I14 -> 1162666 | J15: =J13+J14 -> 1275722.9 | K15: =K13+K14 -> 1184456.7 | ... O15: =O13+O14 -> 1059249.2 | P15: =SUM(D15:O15) -> 15072339
A16: labour | B16: Technician labour (staffing plan + overtime + hires) | D16: =-(Drivers!D13+Assumptions!$H$14*Drivers!D26*Assumptions!$H$43+D94*Assumptions!$H$38+D101*Assumptions!$H$39+Assumptions!$H$15*(Drivers!D10+Drivers!D12)*Assumptions!$H$44) -> -273753.94 | E16: =-(Drivers!E13+Assumptions!$H$14*Drivers!E26*Assumptions!$H$43+E94*Assumptions!$H$38+E101*Assumptions!$H$39+Assumptions!$H$15*(Drivers!E10+Drivers!E12)*Assumptions!$H$44) -> -239427.17 | F16: =-(Drivers!F13+Assumptions!$H$14*Drivers!F26*Assumptions!$H$43+F94*Assumptions!$H$38+F101*Assumptions!$H$39+Assumptions!$H$15*(Drivers!F10+Drivers!F12)*Assumptions!$H$44) -> -262376.16 | G16: =-(Drivers!G13+Assumptions!$H$14*Drivers!G26*Assumptions!$H$43+G94*Assumptions!$H$38+G101*Assumptions!$H$39+Assumptions!$H$15*(Drivers!G10+Drivers!G12)*Assumptions!$H$44) -> -265534.83 | H16: =-(Drivers!H13+Assumptions!$H$14*Drivers!H26*Assumptions!$H$43+H94*Assumptions!$H$38+H101*Assumptions!$H$39+Assumptions!$H$15*(Drivers!H10+Drivers!H12)*Assumptions!$H$44) -> -244269.22 | I16: =-(Drivers!I13+Assumptions!$H$14*Drivers!I26*Assumptions!$H$43+I94*Assumptions!$H$38+I101*Assumptions!$H$39+Assumptions!$H$15*(Drivers!I10+Drivers!I12)*Assumptions!$H$44) -> -282315.27 | J16: =-(Drivers!J13+Assumptions!$H$14*Drivers!J26*Assumptions!$H$43+J94*Assumptions!$H$38+J101*Assumptions!$H$39+Assumptions!$H$15*(Drivers!J10+Drivers!J12)*Assumptions!$H$44) -> -269633.25 | K16: =-(Drivers!K13+Assumptions!$H$14*Drivers!K26*Assumptions!$H$43+K94*Assumptions!$H$38+K101*Assumptions!$H$39+Assumptions!$H$15*(Drivers!K10+Drivers!K12)*Assumptions!$H$44) -> -257892.31 | ... O16: =-(Drivers!O13+Assumptions!$H$14*Drivers!O26*Assumptions!$H$43+O94*Assumptions!$H$38+O101*Assumptions!$H$39+Assumptions!$H$15*(Drivers!O10+Drivers!O12)*Assumptions!$H$44) -> -277668.71 | P16: =SUM(D16:O16) -> -3232720.7
A17: parts | B17: Parts | D17: =-(D8*Assumptions!$H$27+D9*Assumptions!$H$28+(D10+D11+D12)*Assumptions!$H$29)*(1+Assumptions!$H$9) -> -622455.95 | E17: =-(E8*Assumptions!$H$27+E9*Assumptions!$H$28+(E10+E11+E12)*Assumptions!$H$29)*(1+Assumptions!$H$9) -> -570106.06 | F17: =-(F8*Assumptions!$H$27+F9*Assumptions!$H$28+(F10+F11+F12)*Assumptions!$H$29)*(1+Assumptions!$H$9) -> -441625.82 | G17: =-(G8*Assumptions!$H$27+G9*Assumptions!$H$28+(G10+G11+G12)*Assumptions!$H$29)*(1+Assumptions!$H$9) -> -431926.14 | H17: =-(H8*Assumptions!$H$27+H9*Assumptions!$H$28+(H10+H11+H12)*Assumptions!$H$29)*(1+Assumptions!$H$9) -> -432173.69 | I17: =-(I8*Assumptions!$H$27+I9*Assumptions!$H$28+(I10+I11+I12)*Assumptions!$H$29)*(1+Assumptions!$H$9) -> -418110.8 | J17: =-(J8*Assumptions!$H$27+J9*Assumptions!$H$28+(J10+J11+J12)*Assumptions!$H$29)*(1+Assumptions!$H$9) -> -452225.23 | K17: =-(K8*Assumptions!$H$27+K9*Assumptions!$H$28+(K10+K11+K12)*Assumptions!$H$29)*(1+Assumptions!$H$9) -> -414909.72 | ... O17: =-(O8*Assumptions!$H$27+O9*Assumptions!$H$28+(O10+O11+O12)*Assumptions!$H$29)*(1+Assumptions!$H$9) -> -373092.48 | P17: =SUM(D17:O17) -> -5438973
A18: materials | B18: Paint & materials | D18: =-(D8*Assumptions!$H$30+(D10+D12)*Assumptions!$H$31) -> -40848.187 | E18: =-(E8*Assumptions!$H$30+(E10+E12)*Assumptions!$H$31) -> -38799.713 | F18: =-(F8*Assumptions!$H$30+(F10+F12)*Assumptions!$H$31) -> -32475.954 | G18: =-(G8*Assumptions!$H$30+(G10+G12)*Assumptions!$H$31) -> -30452.88 | H18: =-(H8*Assumptions!$H$30+(H10+H12)*Assumptions!$H$31) -> -30169.876 | I18: =-(I8*Assumptions!$H$30+(I10+I12)*Assumptions!$H$31) -> -30139.911 | J18: =-(J8*Assumptions!$H$30+(J10+J12)*Assumptions!$H$31) -> -31202.948 | K18: =-(K8*Assumptions!$H$30+(K10+K12)*Assumptions!$H$31) -> -25754.368 | ... O18: =-(O8*Assumptions!$H$30+(O10+O12)*Assumptions!$H$31) -> -27273.221 | P18: =SUM(D18:O18) -> -384256.61
A19: sublet | B19: Subcontractor costs (sublet repairs & towing) | D19: =-(D8*Assumptions!$H$32+D9*Assumptions!$H$33) -> -21824.505 | E19: =-(E8*Assumptions!$H$32+E9*Assumptions!$H$33) -> -20144.856 | F19: =-(F8*Assumptions!$H$32+F9*Assumptions!$H$33) -> -15659.692 | G19: =-(G8*Assumptions!$H$32+G9*Assumptions!$H$33) -> -14947.877 | H19: =-(H8*Assumptions!$H$32+H9*Assumptions!$H$33) -> -15181.621 | I19: =-(I8*Assumptions!$H$32+I9*Assumptions!$H$33) -> -14104.337 | J19: =-(J8*Assumptions!$H$32+J9*Assumptions!$H$33) -> -15086.659 | K19: =-(K8*Assumptions!$H$32+K9*Assumptions!$H$33) -> -13771.226 | ... O19: =-(O8*Assumptions!$H$32+O9*Assumptions!$H$33) -> -12293.42 | P19: =SUM(D19:O19) -> -185062.88
A20: warranty | B20: Warranty rework - parts & sublet | D20: =-Assumptions!$H$35*D15 -> -1525.2131 | E20: =-Assumptions!$H$35*E15 -> -1381.7936 | F20: =-Assumptions!$H$35*F15 -> -1059.0329 | G20: =-Assumptions!$H$35*G15 -> -1061.5771 | H20: =-Assumptions!$H$35*H15 -> -1049.5165 | I20: =-Assumptions!$H$35*I15 -> -1046.3809 | J20: =-Assumptions!$H$35*J15 -> -1148.1304 | K20: =-Assumptions!$H$35*K15 -> -1065.9922 | ... O20: =-Assumptions!$H$35*O15 -> -953.3075 | P20: =SUM(D20:O20) -> -13564.866
A21: margin_uplift | B21: Gross-margin initiatives (scenario) | D21: =Assumptions!$H$12*(D15+D16+D17+D18+D19+D20) -> 0 | E21: =Assumptions!$H$12*(E15+E16+E17+E18+E19+E20) -> 0 | F21: =Assumptions!$H$12*(F15+F16+F17+F18+F19+F20) -> 0 | G21: =Assumptions!$H$12*(G15+G16+G17+G18+G19+G20) -> 0 | H21: =Assumptions!$H$12*(H15+H16+H17+H18+H19+H20) -> 0 | I21: =Assumptions!$H$12*(I15+I16+I17+I18+I19+I20) -> 0 | J21: =Assumptions!$H$12*(J15+J16+J17+J18+J19+J20) -> 0 | K21: =Assumptions!$H$12*(K15+K16+K17+K18+K19+K20) -> 0 | ... O21: =Assumptions!$H$12*(O15+O16+O17+O18+O19+O20) -> 0 | P21: =SUM(D21:O21) -> 0
A22: cogs | B22: Cost of sales | D22: =D16+D17+D18+D19+D20+D21 -> -960407.79 | E22: =E16+E17+E18+E19+E20+E21 -> -869859.59 | F22: =F16+F17+F18+F19+F20+F21 -> -753196.66 | G22: =G16+G17+G18+G19+G20+G21 -> -743923.3 | H22: =H16+H17+H18+H19+H20+H21 -> -722843.92 | I22: =I16+I17+I18+I19+I20+I21 -> -745716.7 | J22: =J16+J17+J18+J19+J20+J21 -> -769296.22 | K22: =K16+K17+K18+K19+K20+K21 -> -713393.62 | ... O22: =O16+O17+O18+O19+O20+O21 -> -691281.14 | P22: =SUM(D22:O22) -> -9254578
A23: gross_profit | B23: Gross profit | D23: =D15+D22 -> 734303.3 | E23: =E15+E22 -> 665493.72 | F23: =F15+F22 -> 423527.37 | G23: =G15+G22 -> 435627.65 | H23: =H15+H22 -> 443306.08 | I23: =I15+I22 -> 416949.25 | J23: =J15+J22 -> 506426.71 | K23: =K15+K22 -> 471063.09 | ... O23: =O15+O22 -> 367968.1 | P23: =SUM(D23:O23) -> 5817761
A24: staff | B24: Staff compensation | D24: =-Drivers!D14*(1+Assumptions!$H$16) -> -141220.64 | E24: =-Drivers!E14*(1+Assumptions!$H$16) -> -141220.64 | F24: =-Drivers!F14*(1+Assumptions!$H$16) -> -141220.64 | G24: =-Drivers!G14*(1+Assumptions!$H$16) -> -145457.26 | H24: =-Drivers!H14*(1+Assumptions!$H$16) -> -145457.26 | I24: =-Drivers!I14*(1+Assumptions!$H$16) -> -145457.26 | J24: =-Drivers!J14*(1+Assumptions!$H$16) -> -145457.26 | K24: =-Drivers!K14*(1+Assumptions!$H$16) -> -145457.26 | ... O24: =-Drivers!O14*(1+Assumptions!$H$16) -> -145457.26 | P24: =SUM(D24:O24) -> -1732777.3
A25: occupancy | B25: Occupancy (lease schedule, utilities) | D25: =-Drivers!D15 -> -99702.616 | E25: =-Drivers!E15 -> -104967.14 | F25: =-Drivers!F15 -> -105416.81 | G25: =-Drivers!G15 -> -108921.59 | H25: =-Drivers!H15 -> -108259.45 | I25: =-Drivers!I15 -> -108749.05 | J25: =-Drivers!J15 -> -102371.76 | K25: =-Drivers!K15 -> -102558.95 | ... O25: =-Drivers!O15 -> -102666.49 | P25: =SUM(D25:O25) -> -1251505
A26: marketing | B26: Marketing & advertising | D26: =-Drivers!D16*(1+Assumptions!$H$16) -> -10799.995 | E26: =-Drivers!E16*(1+Assumptions!$H$16) -> -10686.671 | F26: =-Drivers!F16*(1+Assumptions!$H$16) -> -10359.285 | G26: =-Drivers!G16*(1+Assumptions!$H$16) -> -9703.962 | H26: =-Drivers!H16*(1+Assumptions!$H$16) -> -10590.864 | I26: =-Drivers!I16*(1+Assumptions!$H$16) -> -9425.0902 | J26: =-Drivers!J16*(1+Assumptions!$H$16) -> -9514.583 | K26: =-Drivers!K16*(1+Assumptions!$H$16) -> -9872.882 | ... O26: =-Drivers!O16*(1+Assumptions!$H$16) -> -9637.7162 | P26: =SUM(D26:O26) -> -122350.45
A27: g_and_a | B27: General & administrative | D27: =-Drivers!D17*(1+Assumptions!$H$16) -> -30221.992 | E27: =-Drivers!E17*(1+Assumptions!$H$16) -> -30354.647 | F27: =-Drivers!F17*(1+Assumptions!$H$16) -> -29455.302 | G27: =-Drivers!G17*(1+Assumptions!$H$16) -> -34314.663 | H27: =-Drivers!H17*(1+Assumptions!$H$16) -> -30551.427 | I27: =-Drivers!I17*(1+Assumptions!$H$16) -> -31001.279 | J27: =-Drivers!J17*(1+Assumptions!$H$16) -> -31503.816 | K27: =-Drivers!K17*(1+Assumptions!$H$16) -> -30906.815 | ... O27: =-Drivers!O17*(1+Assumptions!$H$16) -> -30287.151 | P27: =SUM(D27:O27) -> -371595.42
A28: shop_ops | B28: Shop operations (incl. card fees) | D28: =-(Drivers!D18*(1+Assumptions!$H$16)+Assumptions!$H$45*D15) -> -53114.385 | E28: =-(Drivers!E18*(1+Assumptions!$H$16)+Assumptions!$H$45*E15) -> -51090.601 | F28: =-(Drivers!F18*(1+Assumptions!$H$16)+Assumptions!$H$45*F15) -> -48794.453 | G28: =-(Drivers!G18*(1+Assumptions!$H$16)+Assumptions!$H$45*G15) -> -50157.112 | H28: =-(Drivers!H18*(1+Assumptions!$H$16)+Assumptions!$H$45*H15) -> -47126.035 | I28: =-(Drivers!I18*(1+Assumptions!$H$16)+Assumptions!$H$45*I15) -> -49567.947 | J28: =-(Drivers!J18*(1+Assumptions!$H$16)+Assumptions!$H$45*J15) -> -51884.54 | K28: =-(Drivers!K18*(1+Assumptions!$H$16)+Assumptions!$H$45*K15) -> -52234.681 | ... O28: =-(Drivers!O18*(1+Assumptions!$H$16)+Assumptions!$H$45*O15) -> -50411.012 | P28: =SUM(D28:O28) -> -605881.96
A29: opex | B29: Operating expenses (before depreciation) | D29: =D24+D25+D26+D27+D28 -> -335059.63 | E29: =E24+E25+E26+E27+E28 -> -338319.7 | F29: =F24+F25+F26+F27+F28 -> -335246.49 | G29: =G24+G25+G26+G27+G28 -> -348554.58 | H29: =H24+H25+H26+H27+H28 -> -341985.03 | I29: =I24+I25+I26+I27+I28 -> -344200.62 | J29: =J24+J25+J26+J27+J28 -> -340731.95 | K29: =K24+K25+K26+K27+K28 -> -341030.59 | ... O29: =O24+O25+O26+O27+O28 -> -338459.63 | P29: =SUM(D29:O29) -> -4084110.1
A30: ebitda | B30: EBITDA | D30: =D23+D29 -> 399243.67 | E30: =E23+E29 -> 327174.02 | F30: =F23+F29 -> 88280.875 | G30: =G23+G29 -> 87073.067 | H30: =H23+H29 -> 101321.04 | I30: =I23+I29 -> 72748.629 | J30: =J23+J29 -> 165694.76 | K30: =K23+K29 -> 130032.51 | ... O30: =O23+O29 -> 29508.467 | P30: =SUM(D30:O30) -> 1733650.9
A31: da | B31: Depreciation | D31: =-(Drivers!D23+C106/Assumptions!$H$66) -> -23245.84 | E31: =-(Drivers!E23+D106/Assumptions!$H$66) -> -23245.84 | F31: =-(Drivers!F23+E106/Assumptions!$H$66) -> -23245.84 | G31: =-(Drivers!G23+F106/Assumptions!$H$66) -> -23245.84 | H31: =-(Drivers!H23+G106/Assumptions!$H$66) -> -23245.84 | I31: =-(Drivers!I23+H106/Assumptions!$H$66) -> -23245.84 | J31: =-(Drivers!J23+I106/Assumptions!$H$66) -> -22162.71 | K31: =-(Drivers!K23+J106/Assumptions!$H$66) -> -22162.51 | ... O31: =-(Drivers!O23+N106/Assumptions!$H$66) -> -22162.51 | P31: =SUM(D31:O31) -> -272450.3
A32: ebit | B32: Operating income (EBIT) | D32: =D30+D31 -> 375997.83 | E32: =E30+E31 -> 303928.18 | F32: =F30+F31 -> 65035.035 | G32: =G30+G31 -> 63827.227 | H32: =H30+H31 -> 78075.204 | I32: =I30+I31 -> 49502.789 | J32: =J30+J31 -> 143532.05 | K32: =K30+K31 -> 107870 | ... O32: =O30+O31 -> 7345.9566 | P32: =SUM(D32:O32) -> 1461200.6
A33: interest | B33: Interest expense | D33: =-(C111*(Assumptions!$H$56+Assumptions!$H$17+Assumptions!$H$57)+C56*(Assumptions!$H$56+Assumptions!$H$17+Assumptions!$H$58))/12 -> -2464.2187 | E33: =-(D111*(Assumptions!$H$56+Assumptions!$H$17+Assumptions!$H$57)+D56*(Assumptions!$H$56+Assumptions!$H$17+Assumptions!$H$58))/12 -> -2374.4853 | F33: =-(E111*(Assumptions!$H$56+Assumptions!$H$17+Assumptions!$H$57)+E56*(Assumptions!$H$56+Assumptions!$H$17+Assumptions!$H$58))/12 -> -2284.7518 | G33: =-(F111*(Assumptions!$H$56+Assumptions!$H$17+Assumptions!$H$57)+F56*(Assumptions!$H$56+Assumptions!$H$17+Assumptions!$H$58))/12 -> -2195.0184 | H33: =-(G111*(Assumptions!$H$56+Assumptions!$H$17+Assumptions!$H$57)+G56*(Assumptions!$H$56+Assumptions!$H$17+Assumptions!$H$58))/12 -> -2105.2849 | I33: =-(H111*(Assumptions!$H$56+Assumptions!$H$17+Assumptions!$H$57)+H56*(Assumptions!$H$56+Assumptions!$H$17+Assumptions!$H$58))/12 -> -2015.5515 | J33: =-(I111*(Assumptions!$H$56+Assumptions!$H$17+Assumptions!$H$57)+I56*(Assumptions!$H$56+Assumptions!$H$17+Assumptions!$H$58))/12 -> -1925.818 | K33: =-(J111*(Assumptions!$H$56+Assumptions!$H$17+Assumptions!$H$57)+J56*(Assumptions!$H$56+Assumptions!$H$17+Assumptions!$H$58))/12 -> -1836.0846 | ... O33: =-(N111*(Assumptions!$H$56+Assumptions!$H$17+Assumptions!$H$57)+N56*(Assumptions!$H$56+Assumptions!$H$17+Assumptions!$H$58))/12 -> -1477.1507 | P33: =SUM(D33:O33) -> -23648.217
A34: pbt | B34: Income before tax | D34: =D32+D33 -> 373533.61 | E34: =E32+E33 -> 301553.69 | F34: =F32+F33 -> 62750.284 | G34: =G32+G33 -> 61632.209 | H34: =H32+H33 -> 75969.919 | I34: =I32+I33 -> 47487.238 | J34: =J32+J33 -> 141606.23 | K34: =K32+K33 -> 106033.91 | ... O34: =O32+O33 -> 5868.8059 | P34: =SUM(D34:O34) -> 1437552.4
A35: tax | B35: Income taxes | D35: =-(D116-IF(Drivers!D27,0,C116)) -> -85912.734 | E35: =-(E116-IF(Drivers!E27,0,D116)) -> -69357.349 | F35: =-(F116-IF(Drivers!F27,0,E116)) -> -14432.565 | G35: =-(G116-IF(Drivers!G27,0,F116)) -> -6779.543 | H35: =-(H116-IF(Drivers!H27,0,G116)) -> -8356.6911 | I35: =-(I116-IF(Drivers!I27,0,H116)) -> -5223.5961 | J35: =-(J116-IF(Drivers!J27,0,I116)) -> -15576.685 | K35: =-(K116-IF(Drivers!K27,0,J116)) -> -11663.73 | ... O35: =-(O116-IF(Drivers!O27,0,N116)) -> -1349.8254 | P35: =SUM(D35:O35) -> -270637.05
A36: net_income | B36: Net income | D36: =D34+D35 -> 287620.88 | E36: =E34+E35 -> 232196.34 | F36: =F34+F35 -> 48317.718 | G36: =G34+G35 -> 54852.666 | H36: =H34+H35 -> 67613.228 | I36: =I34+I35 -> 42263.641 | J36: =J34+J35 -> 126029.54 | K36: =K34+K35 -> 94370.182 | ... O36: =O34+O35 -> 4518.9805 | P36: =SUM(D36:O36) -> 1166915.3
A38: BALANCE SHEET (forecast; column C = actual 30-Sep-2026 from the general ledger)
A39: cash | B39: Cash | C39: =Hist_Balances!$AJ$6 -> 1390234 | D39: =C39+D82 -> 1736043.9 | E39: =D39+E82 -> 2045166.7 | F39: =E39+F82 -> 1758471.1 | G39: =F39+G82 -> 1693642.9 | H39: =G39+H82 -> 1809259 | I39: =H39+I82 -> 1536640.5 | J39: =I39+J82 -> 1608448.1 | K39: =J39+K82 -> 1760135.9 | ... O39: =N39+O82 -> 2160422.3
A40: ar_insurer | B40: Insurer receivables | C40: =Hist_Balances!$AJ$8 -> 573560.54 | D40: =Assumptions!$H$47*(1+Assumptions!$H$13)/30.4*Assumptions!$H$46*D15*(1+Assumptions!$H$55) -> 860622.84 | E40: =Assumptions!$H$47*(1+Assumptions!$H$13)/30.4*Assumptions!$H$46*E15*(1+Assumptions!$H$55) -> 779696.39 | F40: =Assumptions!$H$47*(1+Assumptions!$H$13)/30.4*Assumptions!$H$46*F15*(1+Assumptions!$H$55) -> 597574.17 | G40: =Assumptions!$H$47*(1+Assumptions!$H$13)/30.4*Assumptions!$H$46*G15*(1+Assumptions!$H$55) -> 599009.76 | H40: =Assumptions!$H$47*(1+Assumptions!$H$13)/30.4*Assumptions!$H$46*H15*(1+Assumptions!$H$55) -> 592204.38 | I40: =Assumptions!$H$47*(1+Assumptions!$H$13)/30.4*Assumptions!$H$46*I15*(1+Assumptions!$H$55) -> 590435.08 | J40: =Assumptions!$H$47*(1+Assumptions!$H$13)/30.4*Assumptions!$H$46*J15*(1+Assumptions!$H$55) -> 647848.65 | K40: =Assumptions!$H$47*(1+Assumptions!$H$13)/30.4*Assumptions!$H$46*K15*(1+Assumptions!$H$55) -> 601501.05 | ... O40: =Assumptions!$H$47*(1+Assumptions!$H$13)/30.4*Assumptions!$H$46*O15*(1+Assumptions!$H$55) -> 537917.11
A41: ar_other | B41: Card settlements & fleet receivables | C41: =Hist_Balances!$AJ$7+Hist_Balances!$AJ$9 -> 110132.82 | D41: =Assumptions!$H$48*(1+Assumptions!$H$13)*D15*(1+Assumptions!$H$55) -> 120331.44 | E41: =Assumptions!$H$48*(1+Assumptions!$H$13)*E15*(1+Assumptions!$H$55) -> 109016.38 | F41: =Assumptions!$H$48*(1+Assumptions!$H$13)*F15*(1+Assumptions!$H$55) -> 83552.229 | G41: =Assumptions!$H$48*(1+Assumptions!$H$13)*G15*(1+Assumptions!$H$55) -> 83752.953 | H41: =Assumptions!$H$48*(1+Assumptions!$H$13)*H15*(1+Assumptions!$H$55) -> 82801.43 | I41: =Assumptions!$H$48*(1+Assumptions!$H$13)*I15*(1+Assumptions!$H$55) -> 82554.049 | J41: =Assumptions!$H$48*(1+Assumptions!$H$13)*J15*(1+Assumptions!$H$55) -> 90581.558 | K41: =Assumptions!$H$48*(1+Assumptions!$H$13)*K15*(1+Assumptions!$H$55) -> 84101.282 | ... O41: =Assumptions!$H$48*(1+Assumptions!$H$13)*O15*(1+Assumptions!$H$55) -> 75211.038
A42: inventory | B42: Parts inventory | C42: =Hist_Balances!$AJ$10+Hist_Balances!$AJ$11 -> 126398.77 | D42: =-Assumptions!$H$49*D17 -> 206785.21 | E42: =-Assumptions!$H$49*E17 -> 189394.13 | F42: =-Assumptions!$H$49*F17 -> 146711.89 | G42: =-Assumptions!$H$49*G17 -> 143489.57 | H42: =-Assumptions!$H$49*H17 -> 143571.81 | I42: =-Assumptions!$H$49*I17 -> 138900 | J42: =-Assumptions!$H$49*J17 -> 150233.1 | K42: =-Assumptions!$H$49*K17 -> 137836.57 | ... O42: =-Assumptions!$H$49*O17 -> 123944.52
A43: materials_inv | B43: Paint & detailing materials | C43: =Hist_Balances!$AJ$12 -> 11736.47 | D43: =-Assumptions!$H$50*D18 -> 17319.317 | E43: =-Assumptions!$H$50*E18 -> 16450.78 | F43: =-Assumptions!$H$50*F18 -> 13769.555 | G43: =-Assumptions!$H$50*G18 -> 12911.787 | H43: =-Assumptions!$H$50*H18 -> 12791.796 | I43: =-Assumptions!$H$50*I18 -> 12779.091 | J43: =-Assumptions!$H$50*J18 -> 13229.81 | K43: =-Assumptions!$H$50*K18 -> 10919.654 | ... O43: =-Assumptions!$H$50*O18 -> 11563.636
A44: wip | B44: Work in progress - unbilled repair jobs | C44: =Hist_Balances!$AJ$13 -> 115918.75 | D44: =-Assumptions!$H$51*(1+Assumptions!$H$10)/30.4*D22 -> 169768.88 | E44: =-Assumptions!$H$51*(1+Assumptions!$H$10)/30.4*E22 -> 153762.9 | F44: =-Assumptions!$H$51*(1+Assumptions!$H$10)/30.4*F22 -> 133140.69 | G44: =-Assumptions!$H$51*(1+Assumptions!$H$10)/30.4*G22 -> 131501.46 | H44: =-Assumptions!$H$51*(1+Assumptions!$H$10)/30.4*H22 -> 127775.31 | I44: =-Assumptions!$H$51*(1+Assumptions!$H$10)/30.4*I22 -> 131818.47 | J44: =-Assumptions!$H$51*(1+Assumptions!$H$10)/30.4*J22 -> 135986.57 | K44: =-Assumptions!$H$51*(1+Assumptions!$H$10)/30.4*K22 -> 126104.8 | ... O44: =-Assumptions!$H$51*(1+Assumptions!$H$10)/30.4*O22 -> 122196.04
A45: prepaid | B45: Prepaid expenses | C45: =Hist_Balances!$AJ$14 -> 27084.78 | D45: =C45+Drivers!D21-Drivers!D20 -> 18056.52 | E45: =D45+Drivers!E21-Drivers!E20 -> 9028.26 | F45: =E45+Drivers!F21-Drivers!F20 -> 0 | G45: =F45+Drivers!G21-Drivers!G20 -> 103283.29 | H45: =G45+Drivers!H21-Drivers!H20 -> 93893.904 | I45: =H45+Drivers!I21-Drivers!I20 -> 84504.514 | J45: =I45+Drivers!J21-Drivers!J20 -> 75115.123 | K45: =J45+Drivers!K21-Drivers!K20 -> 65725.733 | ... O45: =N45+Drivers!O21-Drivers!O20 -> 28168.171
A46: gst_rec | B46: GST recoverable | C46: =Hist_BS!$AI$13 -> 0 | D46: =MAX(0,-D107) -> 0 | E46: =MAX(0,-E107) -> 0 | F46: =MAX(0,-F107) -> 0 | G46: =MAX(0,-G107) -> 0 | H46: =MAX(0,-H107) -> 0 | I46: =MAX(0,-I107) -> 0 | J46: =MAX(0,-J107) -> 0 | K46: =MAX(0,-K107) -> 0 | ... O46: =MAX(0,-O107) -> 0
A47: current_assets | B47: Total current assets | C47: =Hist_BS!$AI$14 -> 2355066.1 | D47: =D39+D40+D41+D42+D43+D44+D45+D46 -> 3128928.2 | E47: =E39+E40+E41+E42+E43+E44+E45+E46 -> 3302515.5 | F47: =F39+F40+F41+F42+F43+F44+F45+F46 -> 2733219.7 | G47: =G39+G40+G41+G42+G43+G44+G45+G46 -> 2767591.8 | H47: =H39+H40+H41+H42+H43+H44+H45+H46 -> 2862297.7 | I47: =I39+I40+I41+I42+I43+I44+I45+I46 -> 2577631.7 | J47: =J39+J40+J41+J42+J43+J44+J45+J46 -> 2721442.9 | K47: =K39+K40+K41+K42+K43+K44+K45+K46 -> 2786325 | ... O47: =O39+O40+O41+O42+O43+O44+O45+O46 -> 3059422.8
A48: ppe_gross | B48: Fixed assets at cost | C48: =Hist_Balances!$AJ$16+Hist_Balances!$AJ$17+Hist_Balances!$AJ$18+Hist_Balances!$AJ$19 -> 2948000 | D48: =C48+Drivers!D22 -> 2948000 | E48: =D48+Drivers!E22 -> 2948000 | F48: =E48+Drivers!F22 -> 2948000 | G48: =F48+Drivers!G22 -> 2948000 | H48: =G48+Drivers!H22 -> 2948000 | I48: =H48+Drivers!I22 -> 3008000 | J48: =I48+Drivers!J22 -> 3008000 | K48: =J48+Drivers!K22 -> 3008000 | ... O48: =N48+Drivers!O22 -> 3008000
A49: acc_dep | B49: Accumulated depreciation | C49: =Hist_Balances!$AJ$20 -> -1605710 | D49: =C49+D31 -> -1628955.9 | E49: =D49+E31 -> -1652201.7 | F49: =E49+F31 -> -1675447.6 | G49: =F49+G31 -> -1698693.4 | H49: =G49+H31 -> -1721939.2 | I49: =H49+I31 -> -1745185.1 | J49: =I49+J31 -> -1767347.8 | K49: =J49+K31 -> -1789510.3 | ... O49: =N49+O31 -> -1878160.3
A50: ppe_net | B50: Net fixed assets | C50: =Hist_BS!$AI$17 -> 1342290 | D50: =D48+D49 -> 1319044.1 | E50: =E48+E49 -> 1295798.3 | F50: =F48+F49 -> 1272552.4 | G50: =G48+G49 -> 1249306.6 | H50: =H48+H49 -> 1226060.8 | I50: =I48+I49 -> 1262814.9 | J50: =J48+J49 -> 1240652.2 | K50: =K48+K49 -> 1218489.7 | ... O50: =O48+O49 -> 1129839.7
A51: total_assets | B51: TOTAL ASSETS | C51: =Hist_BS!$AI$18 -> 3697356.1 | D51: =D47+D50 -> 4447972.3 | E51: =E47+E50 -> 4598313.8 | F51: =F47+F50 -> 4005772.1 | G51: =G47+G50 -> 4016898.4 | H51: =H47+H50 -> 4088358.4 | I51: =I47+I50 -> 3840446.6 | J51: =J47+J50 -> 3962095.1 | K51: =K47+K50 -> 4004814.7 | ... O51: =O47+O50 -> 4189262.5
A52: ap | B52: Accounts payable (suppliers, sublet & vendors) | C52: =-(Hist_Balances!$AJ$21+Hist_Balances!$AJ$22) -> 526655.94 | D52: =Assumptions!$H$52/30.4*D105*(1+Assumptions!$H$55)+Assumptions!$H$53*(Drivers!D19-D19)*(1+Assumptions!$H$55) -> 967542.55 | E52: =Assumptions!$H$52/30.4*E105*(1+Assumptions!$H$55)+Assumptions!$H$53*(Drivers!E19-E19)*(1+Assumptions!$H$55) -> 812439.27 | F52: =Assumptions!$H$52/30.4*F105*(1+Assumptions!$H$55)+Assumptions!$H$53*(Drivers!F19-F19)*(1+Assumptions!$H$55) -> 645189.02 | G52: =Assumptions!$H$52/30.4*G105*(1+Assumptions!$H$55)+Assumptions!$H$53*(Drivers!G19-G19)*(1+Assumptions!$H$55) -> 683750.37 | H52: =Assumptions!$H$52/30.4*H105*(1+Assumptions!$H$55)+Assumptions!$H$53*(Drivers!H19-H19)*(1+Assumptions!$H$55) -> 680687.67 | I52: =Assumptions!$H$52/30.4*I105*(1+Assumptions!$H$55)+Assumptions!$H$53*(Drivers!I19-I19)*(1+Assumptions!$H$55) -> 663327.86 | J52: =Assumptions!$H$52/30.4*J105*(1+Assumptions!$H$55)+Assumptions!$H$53*(Drivers!J19-J19)*(1+Assumptions!$H$55) -> 711159.82 | K52: =Assumptions!$H$52/30.4*K105*(1+Assumptions!$H$55)+Assumptions!$H$53*(Drivers!K19-K19)*(1+Assumptions!$H$55) -> 641673.66 | ... O52: =Assumptions!$H$52/30.4*O105*(1+Assumptions!$H$55)+Assumptions!$H$53*(Drivers!O19-O19)*(1+Assumptions!$H$55) -> 591618.07
A53: accrued | B53: Accrued payroll | C53: =-Hist_Balances!$AJ$23 -> 211225.52 | D53: =Assumptions!$H$54*(-D16-D24) -> 207487.29 | E53: =Assumptions!$H$54*(-E16-E24) -> 190323.9 | F53: =Assumptions!$H$54*(-F16-F24) -> 201798.4 | G53: =Assumptions!$H$54*(-G16-G24) -> 205496.04 | H53: =Assumptions!$H$54*(-H16-H24) -> 194863.24 | I53: =Assumptions!$H$54*(-I16-I24) -> 213886.26 | J53: =Assumptions!$H$54*(-J16-J24) -> 207545.26 | K53: =Assumptions!$H$54*(-K16-K24) -> 201674.79 | ... O53: =Assumptions!$H$54*(-O16-O24) -> 211562.99
A54: gst_pay | B54: GST payable | C54: =Hist_BS!$AI$21 -> 81285.92 | D54: =MAX(0,D107) -> 37470.11 | E54: =MAX(0,E107) -> 74774.631 | F54: =MAX(0,F107) -> 102508.38 | G54: =MAX(0,G107) -> 25993.446 | H54: =MAX(0,H107) -> 51429.083 | I54: =MAX(0,I107) -> 74569.489 | J54: =MAX(0,J107) -> 29370.784 | K54: =MAX(0,K107) -> 57663.168 | ... O54: =MAX(0,O107) -> 80293.015
A55: tax_payable | B55: Income taxes payable | C55: =-Hist_Balances!$AJ$25 -> 134250.03 | D55: =C55-D35-D118 -> 220162.76 | E55: =D55-E35-E118 -> 289520.11 | F55: =E55-F35-F118 -> 303952.68 | G55: =F55-G35-G118 -> 310732.22 | H55: =G55-H35-H118 -> 319088.91 | I55: =H55-I35-I118 -> 20359.83 | J55: =I55-J35-J118 -> 35936.515 | K55: =J55-K35-K118 -> 47600.246 | ... O55: =N55-O35-O118 -> 100934.4
A56: revolver | B56: Revolving line of credit | C56: =-Hist_Balances!$AJ$26 -> 0 | D56: =C56+D78+D79 -> 0 | E56: =D56+E78+E79 -> 0 | F56: =E56+F78+F79 -> 0 | G56: =F56+G78+G79 -> 0 | H56: =G56+H78+H79 -> 0 | I56: =H56+I78+I79 -> 0 | J56: =I56+J78+J79 -> 0 | K56: =J56+K78+K79 -> 0 | ... O56: =N56+O78+O79 -> 0
A57: term_current | B57: Current portion of term loans | C57: =Hist_BS!$AI$24 -> 195000 | D57: =MIN(D111,Drivers!D25) -> 195000 | E57: =MIN(E111,Drivers!E25) -> 195000 | F57: =MIN(F111,Drivers!F25) -> 195000 | G57: =MIN(G111,Drivers!G25) -> 186250 | H57: =MIN(H111,Drivers!H25) -> 177500 | I57: =MIN(I111,Drivers!I25) -> 168750 | J57: =MIN(J111,Drivers!J25) -> 160000 | K57: =MIN(K111,Drivers!K25) -> 151250 | ... O57: =MIN(O111,Drivers!O25) -> 116250
A58: current_liabilities | B58: Total current liabilities | C58: =Hist_BS!$AI$25 -> 1148417.4 | D58: =D52+D53+D54+D55+D56+D57 -> 1627662.7 | E58: =E52+E53+E54+E55+E56+E57 -> 1562057.9 | F58: =F52+F53+F54+F55+F56+F57 -> 1448448.5 | G58: =G52+G53+G54+G55+G56+G57 -> 1412222.1 | H58: =H52+H53+H54+H55+H56+H57 -> 1423568.9 | I58: =I52+I53+I54+I55+I56+I57 -> 1140893.4 | J58: =J52+J53+J54+J55+J56+J57 -> 1144012.4 | K58: =K52+K53+K54+K55+K56+K57 -> 1099861.9 | ... O58: =O52+O53+O54+O55+O56+O57 -> 1100658.5
A59: term_lt | B59: Term loans (non-current) | C59: =Hist_BS!$AI$26 -> 251250 | D59: =D111-D57 -> 235000 | E59: =E111-E57 -> 218750 | F59: =F111-F57 -> 202500 | G59: =G111-G57 -> 195000 | H59: =H111-H57 -> 187500 | I59: =I111-I57 -> 180000 | J59: =J111-J57 -> 172500 | K59: =K111-K57 -> 165000 | ... O59: =O111-O57 -> 135000
A60: total_liabilities | B60: TOTAL LIABILITIES | C60: =Hist_BS!$AI$27 -> 1399667.4 | D60: =D58+D59 -> 1862662.7 | E60: =E58+E59 -> 1780807.9 | F60: =F58+F59 -> 1650948.5 | G60: =G58+G59 -> 1607222.1 | H60: =H58+H59 -> 1611068.9 | I60: =I58+I59 -> 1320893.4 | J60: =J58+J59 -> 1316512.4 | K60: =K58+K59 -> 1264861.9 | ... O60: =O58+O59 -> 1235658.5
A61: share_capital | B61: Share capital | C61: =-Hist_Balances!$AJ$28 -> 200000 | D61: =C61 -> 200000 | E61: =D61 -> 200000 | F61: =E61 -> 200000 | G61: =F61 -> 200000 | H61: =G61 -> 200000 | I61: =H61 -> 200000 | J61: =I61 -> 200000 | K61: =J61 -> 200000 | ... O61: =N61 -> 200000
A62: retained | B62: Retained earnings | C62: =-(Hist_Balances!$AJ$29+Hist_Balances!$AJ$30) -> 1387373.4 | D62: =C62+IF(Drivers!D29,C63+D36,0)+D80 -> 1387373.4 | E62: =D62+IF(Drivers!E29,D63+E36,0)+E80 -> 1387373.4 | F62: =E62+IF(Drivers!F29,E63+F36,0)+F80 -> 2154823.6 | G62: =F62+IF(Drivers!G29,F63+G36,0)+G80 -> 2154823.6 | H62: =G62+IF(Drivers!H29,G63+H36,0)+H80 -> 2154823.6 | I62: =H62+IF(Drivers!I29,H63+I36,0)+I80 -> 2154823.6 | J62: =I62+IF(Drivers!J29,I63+J36,0)+J80 -> 2154823.6 | K62: =J62+IF(Drivers!K29,J63+K36,0)+K80 -> 2154823.6 | ... O62: =N62+IF(Drivers!O29,N63+O36,0)+O80 -> 2154823.6
A63: cpe | B63: Current-year earnings | C63: =Hist_BS!$AI$30 -> 710315.33 | D63: =IF(Drivers!D29,0,C63+D36) -> 997936.21 | E63: =IF(Drivers!E29,0,D63+E36) -> 1230132.6 | F63: =IF(Drivers!F29,0,E63+F36) -> 0 | G63: =IF(Drivers!G29,0,F63+G36) -> 54852.666 | H63: =IF(Drivers!H29,0,G63+H36) -> 122465.89 | I63: =IF(Drivers!I29,0,H63+I36) -> 164729.54 | J63: =IF(Drivers!J29,0,I63+J36) -> 290759.08 | K63: =IF(Drivers!K29,0,J63+K36) -> 385129.26 | ... O63: =IF(Drivers!O29,0,N63+O36) -> 598780.39
A64: total_equity | B64: TOTAL EQUITY | C64: =Hist_BS!$AI$31 -> 2297688.7 | D64: =D61+D62+D63 -> 2585309.6 | E64: =E61+E62+E63 -> 2817505.9 | F64: =F61+F62+F63 -> 2354823.6 | G64: =G61+G62+G63 -> 2409676.3 | H64: =H61+H62+H63 -> 2477289.5 | I64: =I61+I62+I63 -> 2519553.2 | J64: =J61+J62+J63 -> 2645582.7 | K64: =K61+K62+K63 -> 2739952.9 | ... O64: =O61+O62+O63 -> 2953604
A65: total_le | B65: TOTAL LIABILITIES AND EQUITY | C65: =Hist_BS!$AI$32 -> 3697356.1 | D65: =D60+D64 -> 4447972.3 | E65: =E60+E64 -> 4598313.8 | F65: =F60+F64 -> 4005772.1 | G65: =G60+G64 -> 4016898.4 | H65: =H60+H64 -> 4088358.4 | I65: =I60+I64 -> 3840446.6 | J65: =J60+J64 -> 3962095.1 | K65: =K60+K64 -> 4004814.7 | ... O65: =O60+O64 -> 4189262.5
A67: CASH FLOW STATEMENT (indirect method)
A68: cf_ni | B68: Net income | D68: =D36 -> 287620.88 | E68: =E36 -> 232196.34 | F68: =F36 -> 48317.718 | G68: =G36 -> 54852.666 | H68: =H36 -> 67613.228 | I68: =I36 -> 42263.641 | J68: =J36 -> 126029.54 | K68: =K36 -> 94370.182 | ... O68: =O36 -> 4518.9805 | P68: =SUM(D68:O68) -> 1166915.3
A69: cf_da | B69: Depreciation | D69: =-D31 -> 23245.84 | E69: =-E31 -> 23245.84 | F69: =-F31 -> 23245.84 | G69: =-G31 -> 23245.84 | H69: =-H31 -> 23245.84 | I69: =-I31 -> 23245.84 | J69: =-J31 -> 22162.71 | K69: =-K31 -> 22162.51 | ... O69: =-O31 -> 22162.51 | P69: =SUM(D69:O69) -> 272450.3
A70: d_ar | B70: (Increase) decrease in receivables | D70: =C40+C41-D40-D41 -> -297260.92 | E70: =D40+D41-E40-E41 -> 92241.506 | F70: =E40+E41-F40-F41 -> 207586.38 | G70: =F40+F41-G40-G41 -> -1636.3179 | H70: =G40+G41-H40-H41 -> 7756.9079 | I70: =H40+H41-I40-I41 -> 2016.6807 | J70: =I40+I41-J40-J41 -> -65441.082 | K70: =J40+J41-K40-K41 -> 52827.874 | ... O70: =N40+N41-O40-O41 -> 86616.565 | P70: =SUM(D70:O70) -> 70565.215
A71: d_inv | B71: (Increase) decrease in parts & materials inventory | D71: =C42+C43-D42-D43 -> -85969.29 | E71: =D42+D43-E42-E43 -> 18259.62 | F71: =E42+E43-F42-F43 -> 45363.467 | G71: =F42+F43-G42-G43 -> 4080.0843 | H71: =G42+G43-H42-H43 -> 37.753925 | I71: =H42+H43-I42-I43 -> 4684.5162 | J71: =I42+I43-J42-J43 -> -11783.825 | K71: =J42+J43-K42-K43 -> 14706.687 | ... O71: =N42+N43-O42-O43 -> 20970.175 | P71: =SUM(D71:O71) -> 2627.0792
A72: d_wip | B72: (Increase) decrease in work in progress | D72: =C44-D44 -> -53850.132 | E72: =D44-E44 -> 16005.979 | F72: =E44-F44 -> 20622.215 | G72: =F44-G44 -> 1639.2284 | H72: =G44-H44 -> 3726.1482 | I72: =H44-I44 -> -4043.1633 | J72: =I44-J44 -> -4168.0929 | K72: =J44-K44 -> 9881.7623 | ... O72: =N44-O44 -> 11421.83 | P72: =SUM(D72:O72) -> -6277.2869
A73: d_ap | B73: Increase (decrease) in supplier & vendor payables | D73: =D52-C52 -> 440886.61 | E73: =E52-D52 -> -155103.28 | F73: =F52-E52 -> -167250.25 | G73: =G52-F52 -> 38561.345 | H73: =H52-G52 -> -3062.6972 | I73: =I52-H52 -> -17359.812 | J73: =J52-I52 -> 47831.968 | K73: =K52-J52 -> -69486.164 | ... O73: =O52-N52 -> -87607.336 | P73: =SUM(D73:O73) -> 64962.126
A74: d_other | B74: Other working capital (prepaid, accrued payroll, GST, tax) | D74: =C45-D45+D53-C53+D107-C107+D55-C55 -> 47386.954 | E74: =D45-E45+E53-D53+E107-D107+E55-D55 -> 98526.745 | F74: =E45-F45+F53-E53+F107-E107+F55-E55 -> 62669.072 | G74: =F45-G45+G53-F53+G107-F107+G55-F55 -> -169321.05 | H74: =G45-H45+H53-G53+H107-G107+H55-G55 -> 32548.918 | I74: =H45-I45+I53-H53+I107-H107+I55-H55 -> -247176.26 | J74: =I45-J45+J53-I53+J107-I107+J55-I55 -> -26573.636 | K74: =J45-K45+K53-J53+K107-J107+K55-J55 -> 43475.034 | ... O74: =N45-O45+O53-N53+O107-N107+O55-N55 -> 34905.242 | P74: =SUM(D74:O74) -> -35054.458
A75: cfo | B75: Net cash from operating activities | D75: =D68+D69+D70+D71+D72+D73+D74 -> 362059.95 | E75: =E68+E69+E70+E71+E72+E73+E74 -> 325372.75 | F75: =F68+F69+F70+F71+F72+F73+F74 -> 240554.44 | G75: =G68+G69+G70+G71+G72+G73+G74 -> -48578.199 | H75: =H68+H69+H70+H71+H72+H73+H74 -> 131866.1 | I75: =I68+I69+I70+I71+I72+I73+I74 -> -196368.56 | J75: =J68+J69+J70+J71+J72+J73+J74 -> 88057.586 | K75: =K68+K69+K70+K71+K72+K73+K74 -> 167937.88 | ... O75: =O68+O69+O70+O71+O72+O73+O74 -> 92987.966 | P75: =SUM(D75:O75) -> 1536188.3
A76: cfi | B76: Capital expenditures | D76: =-Drivers!D22 -> 0 | E76: =-Drivers!E22 -> 0 | F76: =-Drivers!F22 -> 0 | G76: =-Drivers!G22 -> 0 | H76: =-Drivers!H22 -> 0 | I76: =-Drivers!I22 -> -60000 | J76: =-Drivers!J22 -> 0 | K76: =-Drivers!K22 -> 0 | ... O76: =-Drivers!O22 -> 0 | P76: =SUM(D76:O76) -> -60000
A77: term_repay | B77: Term-loan principal repayments | D77: =-MIN(Drivers!D24,C111) -> -16250 | E77: =-MIN(Drivers!E24,D111) -> -16250 | F77: =-MIN(Drivers!F24,E111) -> -16250 | G77: =-MIN(Drivers!G24,F111) -> -16250 | H77: =-MIN(Drivers!H24,G111) -> -16250 | I77: =-MIN(Drivers!I24,H111) -> -16250 | J77: =-MIN(Drivers!J24,I111) -> -16250 | K77: =-MIN(Drivers!K24,J111) -> -16250 | ... O77: =-MIN(Drivers!O24,N111) -> -16250 | P77: =SUM(D77:O77) -> -195000
A78: rev_draw | B78: Borrowings (revolver draws) | D78: =IF(D110<Assumptions!$H$60,MIN(Assumptions!$H$59-C56,CEILING(MAX(0,Assumptions!$H$61-D110),Assumptions!$H$63)),0) -> 0 | E78: =IF(E110<Assumptions!$H$60,MIN(Assumptions!$H$59-D56,CEILING(MAX(0,Assumptions!$H$61-E110),Assumptions!$H$63)),0) -> 0 | F78: =IF(F110<Assumptions!$H$60,MIN(Assumptions!$H$59-E56,CEILING(MAX(0,Assumptions!$H$61-F110),Assumptions!$H$63)),0) -> 0 | G78: =IF(G110<Assumptions!$H$60,MIN(Assumptions!$H$59-F56,CEILING(MAX(0,Assumptions!$H$61-G110),Assumptions!$H$63)),0) -> 0 | H78: =IF(H110<Assumptions!$H$60,MIN(Assumptions!$H$59-G56,CEILING(MAX(0,Assumptions!$H$61-H110),Assumptions!$H$63)),0) -> 0 | I78: =IF(I110<Assumptions!$H$60,MIN(Assumptions!$H$59-H56,CEILING(MAX(0,Assumptions!$H$61-I110),Assumptions!$H$63)),0) -> 0 | J78: =IF(J110<Assumptions!$H$60,MIN(Assumptions!$H$59-I56,CEILING(MAX(0,Assumptions!$H$61-J110),Assumptions!$H$63)),0) -> 0 | K78: =IF(K110<Assumptions!$H$60,MIN(Assumptions!$H$59-J56,CEILING(MAX(0,Assumptions!$H$61-K110),Assumptions!$H$63)),0) -> 0 | ... O78: =IF(O110<Assumptions!$H$60,MIN(Assumptions!$H$59-N56,CEILING(MAX(0,Assumptions!$H$61-O110),Assumptions!$H$63)),0) -> 0 | P78: =SUM(D78:O78) -> 0
A79: rev_repay | B79: Revolver repayments | D79: =IF((D110>Assumptions!$H$62)*(C56>0),-MIN(C56,FLOOR(MAX(0,D110-Assumptions!$H$61),Assumptions!$H$63)),0) -> 0 | E79: =IF((E110>Assumptions!$H$62)*(D56>0),-MIN(D56,FLOOR(MAX(0,E110-Assumptions!$H$61),Assumptions!$H$63)),0) -> 0 | F79: =IF((F110>Assumptions!$H$62)*(E56>0),-MIN(E56,FLOOR(MAX(0,F110-Assumptions!$H$61),Assumptions!$H$63)),0) -> 0 | G79: =IF((G110>Assumptions!$H$62)*(F56>0),-MIN(F56,FLOOR(MAX(0,G110-Assumptions!$H$61),Assumptions!$H$63)),0) -> 0 | H79: =IF((H110>Assumptions!$H$62)*(G56>0),-MIN(G56,FLOOR(MAX(0,H110-Assumptions!$H$61),Assumptions!$H$63)),0) -> 0 | I79: =IF((I110>Assumptions!$H$62)*(H56>0),-MIN(H56,FLOOR(MAX(0,I110-Assumptions!$H$61),Assumptions!$H$63)),0) -> 0 | J79: =IF((J110>Assumptions!$H$62)*(I56>0),-MIN(I56,FLOOR(MAX(0,J110-Assumptions!$H$61),Assumptions!$H$63)),0) -> 0 | K79: =IF((K110>Assumptions!$H$62)*(J56>0),-MIN(J56,FLOOR(MAX(0,K110-Assumptions!$H$61),Assumptions!$H$63)),0) -> 0 | ... O79: =IF((O110>Assumptions!$H$62)*(N56>0),-MIN(N56,FLOOR(MAX(0,O110-Assumptions!$H$61),Assumptions!$H$63)),0) -> 0 | P79: =SUM(D79:O79) -> 0
A80: dividends | B80: Dividends paid | D80: =IF(Drivers!D29*(D56<0.005),-FLOOR(MIN(Assumptions!$H$64*MAX(0,D119),MAX(0,D110+D78+D79-Assumptions!$H$65)),1000),0) -> 0 | E80: =IF(Drivers!E29*(E56<0.005),-FLOOR(MIN(Assumptions!$H$64*MAX(0,E119),MAX(0,E110+E78+E79-Assumptions!$H$65)),1000),0) -> 0 | F80: =IF(Drivers!F29*(F56<0.005),-FLOOR(MIN(Assumptions!$H$64*MAX(0,F119),MAX(0,F110+F78+F79-Assumptions!$H$65)),1000),0) -> -511000 | G80: =IF(Drivers!G29*(G56<0.005),-FLOOR(MIN(Assumptions!$H$64*MAX(0,G119),MAX(0,G110+G78+G79-Assumptions!$H$65)),1000),0) -> 0 | H80: =IF(Drivers!H29*(H56<0.005),-FLOOR(MIN(Assumptions!$H$64*MAX(0,H119),MAX(0,H110+H78+H79-Assumptions!$H$65)),1000),0) -> 0 | I80: =IF(Drivers!I29*(I56<0.005),-FLOOR(MIN(Assumptions!$H$64*MAX(0,I119),MAX(0,I110+I78+I79-Assumptions!$H$65)),1000),0) -> 0 | J80: =IF(Drivers!J29*(J56<0.005),-FLOOR(MIN(Assumptions!$H$64*MAX(0,J119),MAX(0,J110+J78+J79-Assumptions!$H$65)),1000),0) -> 0 | K80: =IF(Drivers!K29*(K56<0.005),-FLOOR(MIN(Assumptions!$H$64*MAX(0,K119),MAX(0,K110+K78+K79-Assumptions!$H$65)),1000),0) -> 0 | ... O80: =IF(Drivers!O29*(O56<0.005),-FLOOR(MIN(Assumptions!$H$64*MAX(0,O119),MAX(0,O110+O78+O79-Assumptions!$H$65)),1000),0) -> 0 | P80: =SUM(D80:O80) -> -511000
A81: cff | B81: Net cash from (used in) financing activities | D81: =D77+D78+D79+D80 -> -16250 | E81: =E77+E78+E79+E80 -> -16250 | F81: =F77+F78+F79+F80 -> -527250 | G81: =G77+G78+G79+G80 -> -16250 | H81: =H77+H78+H79+H80 -> -16250 | I81: =I77+I78+I79+I80 -> -16250 | J81: =J77+J78+J79+J80 -> -16250 | K81: =K77+K78+K79+K80 -> -16250 | ... O81: =O77+O78+O79+O80 -> -16250 | P81: =SUM(D81:O81) -> -706000
A82: net_change | B82: Net change in cash | D82: =D75+D76+D81 -> 345809.95 | E82: =E75+E76+E81 -> 309122.75 | F82: =F75+F76+F81 -> -286695.56 | G82: =G75+G76+G81 -> -64828.199 | H82: =H75+H76+H81 -> 115616.1 | I82: =I75+I76+I81 -> -272618.56 | J82: =J75+J76+J81 -> 71807.586 | K82: =K75+K76+K81 -> 151687.88 | ... O82: =O75+O76+O81 -> 76737.966 | P82: =SUM(D82:O82) -> 770188.3
A84: CHECKS
A85: check_bs | B85: Check: assets - liabilities - equity (must be 0) | C85: =Hist_BS!$AI$33 -> 0 | D85: =D51-D65 -> 0 | E85: =E51-E65 -> 0 | F85: =F51-F65 -> 0 | G85: =G51-G65 -> 0 | H85: =H51-H65 -> 0 | I85: =I51-I65 -> 0 | J85: =J51-J65 -> 0 | K85: =K51-K65 -> 0 | ... O85: =O51-O65 -> 0
A86: check_cash | B86: Check: ending cash - (opening cash + net change) (must be 0) | D86: =D39-C39-D82 -> 0 | E86: =E39-D39-E82 -> 0 | F86: =F39-E39-F82 -> 0 | G86: =G39-F39-G82 -> -8.7311491e-11 | H86: =H39-G39-H82 -> -1.1641532e-10 | I86: =I39-H39-I82 -> 0 | J86: =J39-I39-J82 -> 0 | K86: =K39-J39-K82 -> 0 | ... O86: =O39-N39-O82 -> -1.6007107e-10
A88: CAPACITY - collision & mechanical billed hours (demand vs technician capacity)
A89: coll_dem | B89: Collision demand - billed body & paint hours (forecast x volume change) | D89: =Drivers!D6*(1+Assumptions!$H$11) -> 2285.6 | E89: =Drivers!E6*(1+Assumptions!$H$11) -> 2714 | F89: =Drivers!F6*(1+Assumptions!$H$11) -> 2288.9 | G89: =Drivers!G6*(1+Assumptions!$H$11) -> 2199.2 | H89: =Drivers!H6*(1+Assumptions!$H$11) -> 2254.1 | I89: =Drivers!I6*(1+Assumptions!$H$11) -> 2082 | J89: =Drivers!J6*(1+Assumptions!$H$11) -> 2057.9 | K89: =Drivers!K6*(1+Assumptions!$H$11) -> 1678.7 | ... O89: =Drivers!O6*(1+Assumptions!$H$11) -> 1718 | P89: =SUM(D89:O89) -> 25451.1
A90: coll_cap | B90: Collision regular capacity - billed hours (capacity x efficiency + hires) | D90: =Drivers!D8*(1+Assumptions!$H$8)+Assumptions!$H$14*Drivers!D26*Assumptions!$H$42*(1+Assumptions!$H$8) -> 2713.7915 | E90: =Drivers!E8*(1+Assumptions!$H$8)+Assumptions!$H$14*Drivers!E26*Assumptions!$H$42*(1+Assumptions!$H$8) -> 2648.6804 | F90: =Drivers!F8*(1+Assumptions!$H$8)+Assumptions!$H$14*Drivers!F26*Assumptions!$H$42*(1+Assumptions!$H$8) -> 2372.2778 | G90: =Drivers!G8*(1+Assumptions!$H$8)+Assumptions!$H$14*Drivers!G26*Assumptions!$H$42*(1+Assumptions!$H$8) -> 2621.7278 | H90: =Drivers!H8*(1+Assumptions!$H$8)+Assumptions!$H$14*Drivers!H26*Assumptions!$H$42*(1+Assumptions!$H$8) -> 2478.8523 | I90: =Drivers!I8*(1+Assumptions!$H$8)+Assumptions!$H$14*Drivers!I26*Assumptions!$H$42*(1+Assumptions!$H$8) -> 2836.5126 | J90: =Drivers!J8*(1+Assumptions!$H$8)+Assumptions!$H$14*Drivers!J26*Assumptions!$H$42*(1+Assumptions!$H$8) -> 2912.53 | K90: =Drivers!K8*(1+Assumptions!$H$8)+Assumptions!$H$14*Drivers!K26*Assumptions!$H$42*(1+Assumptions!$H$8) -> 2601.6664 | ... O90: =Drivers!O8*(1+Assumptions!$H$8)+Assumptions!$H$14*Drivers!O26*Assumptions!$H$42*(1+Assumptions!$H$8) -> 2756.6342
A91: coll_ot_cap | B91: Collision overtime capacity - billed hours | D91: =Assumptions!$H$40*Drivers!D8 -> 271.37915 | E91: =Assumptions!$H$40*Drivers!E8 -> 264.86804 | F91: =Assumptions!$H$40*Drivers!F8 -> 237.22778 | G91: =Assumptions!$H$40*Drivers!G8 -> 262.17278 | H91: =Assumptions!$H$40*Drivers!H8 -> 247.88523 | I91: =Assumptions!$H$40*Drivers!I8 -> 283.65126 | J91: =Assumptions!$H$40*Drivers!J8 -> 291.253 | K91: =Assumptions!$H$40*Drivers!K8 -> 260.16664 | ... O91: =Assumptions!$H$40*Drivers!O8 -> 275.66342
A92: coll_queue | B92: Collision backlog carried in - billed hours | D92: =C95*(1-Assumptions!$H$41*(1+Assumptions!$H$10)) -> 1163.8119 | E92: =D95*(1-Assumptions!$H$41*(1+Assumptions!$H$10)) -> 394.60507 | F92: =E95*(1-Assumptions!$H$41*(1+Assumptions!$H$10)) -> 165.79812 | G92: =F95*(1-Assumptions!$H$41*(1+Assumptions!$H$10)) -> 0 | H92: =G95*(1-Assumptions!$H$41*(1+Assumptions!$H$10)) -> 0 | I92: =H95*(1-Assumptions!$H$41*(1+Assumptions!$H$10)) -> 0 | J92: =I95*(1-Assumptions!$H$41*(1+Assumptions!$H$10)) -> 0 | K92: =J95*(1-Assumptions!$H$41*(1+Assumptions!$H$10)) -> 0 | ... O92: =N95*(1-Assumptions!$H$41*(1+Assumptions!$H$10)) -> 0
A93: coll_hours | B93: Collision billed hours delivered | D93: =MIN(D89+D92,D90+D91) -> 2985.1706 | E93: =MIN(E89+E92,E90+E91) -> 2913.5485 | F93: =MIN(F89+F92,F90+F91) -> 2454.6981 | G93: =MIN(G89+G92,G90+G91) -> 2199.2 | H93: =MIN(H89+H92,H90+H91) -> 2254.1 | I93: =MIN(I89+I92,I90+I91) -> 2082 | J93: =MIN(J89+J92,J90+J91) -> 2057.9 | K93: =MIN(K89+K92,K90+K91) -> 1678.7 | ... O93: =MIN(O89+O92,O90+O91) -> 1718 | P93: =SUM(D93:O93) -> 26516.017
A94: coll_ot | B94: Collision overtime used - billed hours | D94: =MAX(0,D93-D90) -> 271.37915 | E94: =MAX(0,E93-E90) -> 264.86804 | F94: =MAX(0,F93-F90) -> 82.420342 | G94: =MAX(0,G93-G90) -> 0 | H94: =MAX(0,H93-H90) -> 0 | I94: =MAX(0,I93-I90) -> 0 | J94: =MAX(0,J93-J90) -> 0 | K94: =MAX(0,K93-K90) -> 0 | ... O94: =MAX(0,O93-O90) -> 0 | P94: =SUM(D94:O94) -> 618.66753
A95: coll_backlog | B95: Collision backlog waiting at month end - billed hours | C95: 1369.1905 | D95: =D89+D92-D93 -> 464.24126 | E95: =E89+E92-E93 -> 195.05661 | F95: =F89+F92-F93 -> 0 | G95: =G89+G92-G93 -> 0 | H95: =H89+H92-H93 -> 0 | I95: =I89+I92-I93 -> 0 | J95: =J89+J92-J93 -> 0 | K95: =K89+K92-K93 -> 0 | ... O95: =O89+O92-O93 -> 0
A96: mech_dem | B96: Mechanical demand - billed hours | D96: =Drivers!D7*(1+Assumptions!$H$11) -> 1278.0768 | E96: =Drivers!E7*(1+Assumptions!$H$11) -> 1093.5014 | F96: =Drivers!F7*(1+Assumptions!$H$11) -> 640.81542 | G96: =Drivers!G7*(1+Assumptions!$H$11) -> 770.30167 | H96: =Drivers!H7*(1+Assumptions!$H$11) -> 759.74213 | I96: =Drivers!I7*(1+Assumptions!$H$11) -> 719.22129 | J96: =Drivers!J7*(1+Assumptions!$H$11) -> 955.6846 | K96: =Drivers!K7*(1+Assumptions!$H$11) -> 1092.5229 | ... O96: =Drivers!O7*(1+Assumptions!$H$11) -> 733.43261 | P96: =SUM(D96:O96) -> 10225.266
A97: mech_cap | B97: Mechanical regular capacity - billed hours | D97: =Drivers!D9*(1+Assumptions!$H$8) -> 1408.5736 | E97: =Drivers!E9*(1+Assumptions!$H$8) -> 1361.8048 | F97: =Drivers!F9*(1+Assumptions!$H$8) -> 1260.7605 | G97: =Drivers!G9*(1+Assumptions!$H$8) -> 1366.2447 | H97: =Drivers!H9*(1+Assumptions!$H$8) -> 1300.8407 | I97: =Drivers!I9*(1+Assumptions!$H$8) -> 1467.7622 | J97: =Drivers!J9*(1+Assumptions!$H$8) -> 1511.0391 | K97: =Drivers!K9*(1+Assumptions!$H$8) -> 1343.141 | ... O97: =Drivers!O9*(1+Assumptions!$H$8) -> 1429.8814
A98: mech_ot_cap | B98: Mechanical overtime capacity - billed hours | D98: =Assumptions!$H$40*Drivers!D9 -> 140.85736 | E98: =Assumptions!$H$40*Drivers!E9 -> 136.18048 | F98: =Assumptions!$H$40*Drivers!F9 -> 126.07605 | G98: =Assumptions!$H$40*Drivers!G9 -> 136.62447 | H98: =Assumptions!$H$40*Drivers!H9 -> 130.08407 | I98: =Assumptions!$H$40*Drivers!I9 -> 146.77622 | J98: =Assumptions!$H$40*Drivers!J9 -> 151.10391 | K98: =Assumptions!$H$40*Drivers!K9 -> 134.3141 | ... O98: =Assumptions!$H$40*Drivers!O9 -> 142.98814
A99: mech_queue | B99: Mechanical backlog carried in - billed hours | D99: =C102*(1-Assumptions!$H$41*(1+Assumptions!$H$10)) -> 95.396213 | E99: =D102*(1-Assumptions!$H$41*(1+Assumptions!$H$10)) -> 0 | F99: =E102*(1-Assumptions!$H$41*(1+Assumptions!$H$10)) -> 0 | G99: =F102*(1-Assumptions!$H$41*(1+Assumptions!$H$10)) -> 0 | H99: =G102*(1-Assumptions!$H$41*(1+Assumptions!$H$10)) -> 0 | I99: =H102*(1-Assumptions!$H$41*(1+Assumptions!$H$10)) -> 0 | J99: =I102*(1-Assumptions!$H$41*(1+Assumptions!$H$10)) -> 0 | K99: =J102*(1-Assumptions!$H$41*(1+Assumptions!$H$10)) -> 0 | ... O99: =N102*(1-Assumptions!$H$41*(1+Assumptions!$H$10)) -> 0
A100: mech_hours | B100: Mechanical billed hours delivered | D100: =MIN(D96+D99,D97+D98) -> 1373.4731 | E100: =MIN(E96+E99,E97+E98) -> 1093.5014 | F100: =MIN(F96+F99,F97+F98) -> 640.81542 | G100: =MIN(G96+G99,G97+G98) -> 770.30167 | H100: =MIN(H96+H99,H97+H98) -> 759.74213 | I100: =MIN(I96+I99,I97+I98) -> 719.22129 | J100: =MIN(J96+J99,J97+J98) -> 955.6846 | K100: =MIN(K96+K99,K97+K98) -> 1092.5229 | ... O100: =MIN(O96+O99,O97+O98) -> 733.43261 | P100: =SUM(D100:O100) -> 10320.663
A101: mech_ot | B101: Mechanical overtime used - billed hours | D101: =MAX(0,D100-D97) -> 0 | E101: =MAX(0,E100-E97) -> 0 | F101: =MAX(0,F100-F97) -> 0 | G101: =MAX(0,G100-G97) -> 0 | H101: =MAX(0,H100-H97) -> 0 | I101: =MAX(0,I100-I97) -> 0 | J101: =MAX(0,J100-J97) -> 0 | K101: =MAX(0,K100-K97) -> 0 | ... O101: =MAX(0,O100-O97) -> 0 | P101: =SUM(D101:O101) -> 0
A102: mech_backlog | B102: Mechanical backlog waiting at month end - billed hours | C102: 112.23084 | D102: =D96+D99-D100 -> 0 | E102: =E96+E99-E100 -> 0 | F102: =F96+F99-F100 -> 0 | G102: =G96+G99-G100 -> 0 | H102: =H96+H99-H100 -> 0 | I102: =I96+I99-I100 -> 0 | J102: =J96+J99-J100 -> 0 | K102: =K96+K99-K100 -> 0 | ... O102: =O96+O99-O100 -> 0
A104: SUPPORTING SCHEDULES - purchases, capex & working capital
A105: purchases | B105: Parts & materials purchases at cost (memo) | D105: =-D17-D18-D20+D42-C42+D43-C43 -> 750798.64 | E105: =-E17-E18-E20+E42-D42+E43-D43 -> 592027.95 | F105: =-F17-F18-F20+F42-E42+F43-E43 -> 429797.34 | G105: =-G17-G18-G20+G42-F42+G43-F43 -> 459360.51 | H105: =-H17-H18-H20+H42-G42+H43-G43 -> 463355.32 | I105: =-I17-I18-I20+I42-H42+I43-H43 -> 444612.58 | J105: =-J17-J18-J20+J42-I42+J43-I43 -> 496360.13 | K105: =-K17-K18-K20+K42-J42+K43-J43 -> 427023.4 | ... O105: =-O17-O18-O20+O42-N42+O43-N43 -> 380348.83 | P105: =SUM(D105:O105) -> 5834167.4
A106: capex_cum | B106: Cumulative new capex (memo) | C106: 0 | D106: =C106+Drivers!D22 -> 0 | E106: =D106+Drivers!E22 -> 0 | F106: =E106+Drivers!F22 -> 0 | G106: =F106+Drivers!G22 -> 0 | H106: =G106+Drivers!H22 -> 0 | I106: =H106+Drivers!I22 -> 60000 | J106: =I106+Drivers!J22 -> 60000 | K106: =J106+Drivers!K22 -> 60000 | ... O106: =N106+Drivers!O22 -> 60000
A107: gst_net | B107: Net GST payable / (recoverable) (memo) | C107: =-(Hist_Balances!$AJ$15+Hist_Balances!$AJ$24) -> 81285.92 | D107: =C107+Assumptions!$H$55*(D15-D105+D19-Drivers!D19-Drivers!D22)-D108 -> 37470.11 | E107: =D107+Assumptions!$H$55*(E15-E105+E19-Drivers!E19-Drivers!E22)-E108 -> 74774.631 | F107: =E107+Assumptions!$H$55*(F15-F105+F19-Drivers!F19-Drivers!F22)-F108 -> 102508.38 | G107: =F107+Assumptions!$H$55*(G15-G105+G19-Drivers!G19-Drivers!G22)-G108 -> 25993.446 | H107: =G107+Assumptions!$H$55*(H15-H105+H19-Drivers!H19-Drivers!H22)-H108 -> 51429.083 | I107: =H107+Assumptions!$H$55*(I15-I105+I19-Drivers!I19-Drivers!I22)-I108 -> 74569.489 | J107: =I107+Assumptions!$H$55*(J15-J105+J19-Drivers!J19-Drivers!J22)-J108 -> 29370.784 | K107: =J107+Assumptions!$H$55*(K15-K105+K19-Drivers!K19-Drivers!K22)-K108 -> 57663.168 | ... O107: =N107+Assumptions!$H$55*(O15-O105+O19-Drivers!O19-Drivers!O22)-O108 -> 80293.015
...

Sheet Scenario_Results
A1: ⚠ SIMULATED FINANCIAL INFORMATION - synthetic demonstration accounts of a fictional auto care group, not actual company records. Synthetic data generated for a VisiVault Analytics proof of concept (seed 20240103). Fictional auto care group.
A2: Scenario comparison and sensitivity analysis (values computed by the Python engine at build time)
A3: The Forecast sheet recalculates live for the scenario selected on Assumptions; this sheet stores all three for comparison.
B5: Conservative | C5: Base | D5: Optimistic
A6: net_revenue | B6: 14201963 | C6: 15072339 | D6: 15957254
A7: gross_profit | B7: 5144721.9 | C7: 5817761 | D7: 6460218.4
A8: gross_margin_pct | B8: 36.225429 | C8: 38.598926 | D8: 40.484524
A9: ebitda | B9: 1012373.9 | C9: 1733650.9 | D9: 2369754.2
A10: operating_profit | B10: 739923.6 | C10: 1461200.6 | D10: 2097303.9
A11: net_income | B11: 570260.75 | C11: 1166915.3 | D11: 1656714.9
A12: net_margin_pct | B12: 4.0153658 | C12: 7.7420984 | D12: 10.382205
A13: cfo | B13: 794257.23 | C13: 1536188.3 | D13: 2188678
A14: closing_cash | B14: 1477491.2 | C14: 2160422.3 | D14: 2760912
A15: min_cash | B15: 1205281.4 | C15: 1536640.5 | D15: 1821336.8
A16: peak_revolver | B16: 0 | C16: 0 | D16: 0
A17: closing_working_capital | B17: 1421109.8 | C17: 1958764.3 | D17: 2396563.9
... A26: max_abs_cash_check | B26: 1.1641532e-10 | C26: 1.1641532e-10 | D26: 2.0372681e-10
A29: Sensitivity analysis (one driver at a time vs Base)
A30: scenario | B30: driver | C30: value | D30: delta_net_revenue | E30: delta_gross_profit | F30: delta_operating_profit | G30: delta_net_income | H30: delta_cfo | I30: delta_closing_cash | J30: delta_working_capital | K30: delta_collision_hours | L30: delta_overtime_hours | M30: net_income | N30: closing_cash
A31: 10% improvement in technician efficiency | B31: eff_change | C31: 0.1 | D31: 24236.79 | E31: 34191.407 | F31: 34017.375 | G31: 26193.379 | H31: 26193.379 | I31: 16193.379 | J31: 16193.379 | K31: 69.965364 | L31: -347.28838 | M31: 1193108.7 | N31: 2176615.7
A32: 5% reduction in parts procurement costs | B32: parts_cost_change | C32: -0.05 | D32: 0 | E32: 271948.65 | F32: 271948.65 | G32: 209400.46 | H32: 248015.45 | I32: 223015.45 | J32: 184400.46 | K32: 0 | L32: 0 | M32: 1376315.8 | N32: 2383437.7
A33: 15% reduction in average repair cycle time | B33: cycle_change | C33: -0.15 | D33: 13745.84 | E33: 5395.2444 | F33: 5296.543 | G33: 4078.3381 | H33: 22407.744 | I33: 20407.744 | J33: 2078.3381 | K33: 36.954268 | L33: 36.954268 | M33: 1170993.7 | N33: 2180830
A34: 10% increase in appointment volume | B34: appt_change | C34: 0.1 | D34: 1406285.1 | E34: 822291.12 | F34: 812193.35 | G34: 625388.88 | H34: 754274.96 | I34: 720274.96 | J34: 591388.88 | K34: 2370.4885 | L34: 352.27835 | M34: 1792304.2 | N34: 2880697.3
A35: 5% improvement in gross margin | B35: margin_change | C35: 0.05 | D35: 0 | E35: 290888.05 | F35: 290888.05 | G35: 223983.8 | H35: 273172.06 | I35: 245172.06 | J35: 195983.8 | K35: 0 | L35: 0 | M35: 1390899.1 | N35: 2405594.4
A36: 20% reduction in receivables collection delays | B36: collect_change | C36: -0.2 | D36: 0 | E36: 0 | F36: 0 | G36: 0 | H36: 122625.63 | I36: 122625.63 | J36: 0 | K36: 0 | L36: 0 | M36: 1166915.3 | N36: 2283047.9
A37: Hire 2 additional collision technicians | B37: hires | C37: 2 | D37: 0 | E37: -148342.9 | F37: -148342.9 | G37: -114224.03 | H37: -141002.97 | I37: -138002.97 | J37: -111224.03 | K37: 0 | L37: -82.420342 | M37: 1052691.3 | N37: 2022419.3
A38: 25% expansion of detailing & paint protection | B38: expansion | C38: 0.25 | D38: 335141.99 | E38: 189770.37 | F38: 187363.89 | G38: 144270.2 | H38: 170876.16 | I38: 161876.16 | J38: 135270.2 | K38: 0 | L38: 0 | M38: 1311185.5 | N38: 2322298.5
A39: Operating expenses -5% | B39: opex_change | C39: -0.05 | D39: 0 | E39: 0 | F39: 136218.94 | G39: 104888.58 | H39: 124913.2 | I39: 114913.2 | J39: 94888.584 | K39: 0 | L39: 0 | M39: 1271803.9 | N39: 2275335.5
A40: Prime rate +100 bps | B40: rate_change | C40: 0.01 | D40: 0 | E40: 0 | F40: 0 | G40: -2747.9375 | H40: -3321.5 | I40: -3321.5 | J40: -2747.9375 | K40: 0 | L40: 0 | M40: 1164167.4 | N40: 2157100.8
A43: LIVE: active scenario (formulas on the Forecast sheet)
A44: Net revenue | B44: =SUM(Forecast!D15:O15) -> 15072339
A45: Net income | B45: =SUM(Forecast!D36:O36) -> 1166915.3
A46: Closing cash Sep-2027 | B46: =Forecast!O39 -> 2160422.3
A47: Minimum month-end cash | B47: =MIN(Forecast!D39:O39) -> 1536640.5
A48: Peak revolver | B48: =MAX(0,MAX(Forecast!D56:O56)) -> 0
A49: Insurer receivables Sep-2027 | B49: =Forecast!O40 -> 537917.11
A50: Max |balance-sheet check| | B50: =MAX(ABS(MIN(Forecast!D85:O85)),ABS(MAX(Forecast!D85:O85))) -> 0

Sheet Checks
A1: ⚠ SIMULATED FINANCIAL INFORMATION - synthetic demonstration accounts of a fictional auto care group, not actual company records. Synthetic data generated for a VisiVault Analytics proof of concept (seed 20240103). Fictional auto care group.
A2: Model integrity checks (live formulas - every value must be 0 / TRUE)
A5: Check | B5: Value | C5: Pass?
A6: Trial balance: max |sum of account balances| (Dec-2023 to Sep-2026) | B6: =MAX(ABS(MIN(Hist_Balances!$C$64:$AJ$64)),ABS(MAX(Hist_Balances!$C$64:$AJ$64))) -> 0 | C6: =ABS(B6)<0.01 -> TRUE
A7: Historical balance sheet: max |assets - liabilities - equity| | B7: =MAX(ABS(MIN(Hist_BS!C33:AI33)),ABS(MAX(Hist_BS!C33:AI33))) -> 0 | C7: =ABS(B7)<0.01 -> TRUE
A8: Historical cash flow: max |closing cash - balance-sheet cash| | B8: =MAX(ABS(MIN(Hist_CF!C24:AI24)),ABS(MAX(Hist_CF!C24:AI24))) -> 0 | C8: =ABS(B8)<0.01 -> TRUE
A9: Forecast balance sheet: max |assets - liabilities - equity| | B9: =MAX(ABS(MIN(Forecast!D85:O85)),ABS(MAX(Forecast!D85:O85))) -> 0 | C9: =ABS(B9)<0.01 -> TRUE
A10: Forecast cash flow: max |closing cash - balance-sheet cash| | B10: =MAX(ABS(MIN(Forecast!D86:O86)),ABS(MAX(Forecast!D86:O86))) -> 1.6007107e-10 | C10: =ABS(B10)<0.01 -> TRUE
A11: Forecast opening cash = historical closing cash (Sep-2026) | B11: =ROUND(Forecast!C39-Hist_BS!AI6,2) -> 0 | C11: =ABS(B11)<0.01 -> TRUE
A12: ALL CHECKS PASS | C12: =AND(C6:C11) -> TRUE

Sheet Hist_IS
A1: ⚠ SIMULATED FINANCIAL INFORMATION - synthetic demonstration accounts of a fictional auto care group, not actual company records. Synthetic data generated for a VisiVault Analytics proof of concept (seed 20240103). Fictional auto care group.
A2: Historical income statements - consolidated, interbranch eliminated (CAD)
A3: Monthly values from the general ledger; subtotal rows are live formulas. FY columns sum the months.
A5: Line | B5: Key | C5: 2024-01 | D5: 2024-02 | E5: 2024-03 | F5: 2024-04 | G5: 2024-05 | H5: 2024-06 | I5: 2024-07 | J5: 2024-08 | K5: 2024-09 | L5: 2024-10 | M5: 2024-11 | N5: 2024-12 | O5: 2025-01 | P5: 2025-02 | Q5: 2025-03 | R5: 2025-04 | S5: 2025-05 | T5: 2025-06 | U5: 2025-07 | V5: 2025-08 | W5: 2025-09 | X5: 2025-10 | Y5: 2025-11 | Z5: 2025-12 | AA5: 2026-01 | AB5: 2026-02 | AC5: 2026-03 | AD5: 2026-04 | AE5: 2026-05 | AF5: 2026-06 | AG5: 2026-07 | AH5: 2026-08 | AI5: 2026-09 | AJ5: FY2024 | AK5: FY2025 | AL5: YTD Sep-2026
A6: Collision repair revenue | B6: rev_collision | C6: 535748.84 | D6: 697212.33 | E6: 600100.5 | F6: 635993.75 | G6: 641852.68 | H6: 385344.1 | I6: 381913.17 | J6: 416953.28 | K6: 646361.59 | L6: 538820.54 | M6: 576821.13 | N6: 532711.48 | O6: 699721.5 | P6: 617088.75 | Q6: 648451.89 | R6: 499351.84 | S6: 668416.45 | T6: 548686.8 | U6: 624666.58 | V6: 765727.54 | W6: 657986.31 | X6: 657157.08 | Y6: 563695.48 | Z6: 729662.15 | AA6: 1115733.1 | AB6: 831639.92 | AC6: 819803.78 | AD6: 796755.85 | AE6: 628523.38 | AF6: 643079.8 | AG6: 674357.74 | AH6: 757456.93 | AI6: 667874.6 | AJ6: =SUM(C6:N6) -> 6589833.4 | AK6: =SUM(O6:Z6) -> 7680612.4 | AL6: =SUM(AA6:AI6) -> 6935225.1
A7: Mechanical service revenue | B7: rev_mech | C7: 185909.12 | D7: 187246.52 | E7: 154214.04 | F7: 266248.4 | G7: 313601.58 | H7: 208274.83 | I7: 169098 | J7: 178348.41 | K7: 190058.5 | L7: 369088.9 | M7: 347868.64 | N7: 171743.08 | O7: 186033.77 | P7: 218788.91 | Q7: 203322.18 | R7: 260923.49 | S7: 343077.28 | T7: 228817.78 | U7: 224374.52 | V7: 214544.27 | W7: 213509.76 | X7: 405072.41 | Y7: 440663.15 | Z7: 215245.71 | AA7: 270709.69 | AB7: 213835.05 | AC7: 238018.94 | AD7: 383098.24 | AE7: 439580.36 | AF7: 311008.96 | AG7: 236370.23 | AH7: 248304.35 | AI7: 260873.48 | AJ7: =SUM(C7:N7) -> 2741700 | AK7: =SUM(O7:Z7) -> 3154373.2 | AL7: =SUM(AA7:AI7) -> 2601799.3
A8: Detailing revenue | B8: rev_detail | C8: 6032.6 | D8: 5684.6 | E8: 12470 | F8: 15892.8 | G8: 13975 | H8: 15239.2 | I8: 16348.6 | J8: 19350 | K8: 10939.2 | L8: 13192.4 | M8: 9262.2 | N8: 7817.4 | O8: 10414.8 | P8: 7272 | Q8: 10368 | R8: 17118 | S8: 30357 | T8: 37665 | U8: 34749 | V8: 30798 | W8: 36225 | X8: 33669 | Y8: 17604 | Z8: 22329 | AA8: 22839.8 | AB8: 24195.6 | AC8: 38295.6 | AD8: 61513.6 | AE8: 57659.6 | AF8: 66204.2 | AG8: 42121.4 | AH8: 53335.6 | AI8: 55826.6 | AJ8: =SUM(C8:N8) -> 146204 | AK8: =SUM(O8:Z8) -> 288568.8 | AL8: =SUM(AA8:AI8) -> 421992
A9: Glass repair revenue | B9: rev_glass | C9: 36990.19 | D9: 28679.49 | E9: 37116.23 | F9: 49812.14 | G9: 46379.55 | H9: 37325.37 | I9: 36745.57 | J9: 39138.71 | K9: 25593.51 | L9: 38664.88 | M9: 33297.28 | N9: 20253.07 | O9: 34216.23 | P9: 29155.72 | Q9: 54639.62 | R9: 40927.86 | S9: 58813.24 | T9: 46501.84 | U9: 36182.69 | V9: 50513.56 | W9: 27530.72 | X9: 37789.39 | Y9: 39084.16 | Z9: 31715.35 | AA9: 37113.25 | AB9: 38630.76 | AC9: 50478.39 | AD9: 52260.8 | AE9: 52842.69 | AF9: 44753.98 | AG9: 45201.94 | AH9: 69551.56 | AI9: 53702.35 | AJ9: =SUM(C9:N9) -> 429995.99 | AK9: =SUM(O9:Z9) -> 487070.38 | AL9: =SUM(AA9:AI9) -> 444535.72
A10: Other service revenue (PDR, paint protection, ADAS, fees) | B10: rev_other | C10: 8595.16 | D10: 6625.65 | E10: 9074.35 | F10: 8669 | G10: 9262.97 | H10: 8337.47 | I10: 7424.71 | J10: 48418.62 | K10: 17771.2 | L10: 12649.76 | M10: 9651.44 | N10: 10124.96 | O10: 9919.63 | P10: 9412.9 | Q10: 12579.49 | R10: 8922.78 | S10: 18835.23 | T10: 30291.58 | U10: 56356.25 | V10: 80300.51 | W10: 54704.21 | X10: 44844.94 | Y10: 38056.74 | Z10: 22726.79 | AA10: 46911.53 | AB10: 29218.25 | AC10: 62981.53 | AD10: 77274.89 | AE10: 54051.37 | AF10: 86525.79 | AG10: 141310.65 | AH10: 74340.63 | AI10: 90328.55 | AJ10: =SUM(C10:N10) -> 156605.29 | AK10: =SUM(O10:Z10) -> 386951.05 | AL10: =SUM(AA10:AI10) -> 662943.19
A11: Service revenue | B11: gross_rev | C11: =C6+C7+C8+C9+C10 -> 773275.91 | D11: =D6+D7+D8+D9+D10 -> 925448.59 | E11: =E6+E7+E8+E9+E10 -> 812975.12 | F11: =F6+F7+F8+F9+F10 -> 976616.09 | G11: =G6+G7+G8+G9+G10 -> 1025071.8 | H11: =H6+H7+H8+H9+H10 -> 654520.97 | I11: =I6+I7+I8+I9+I10 -> 611530.05 | J11: =J6+J7+J8+J9+J10 -> 702209.02 | ... AI11: =AI6+AI7+AI8+AI9+AI10 -> 1128605.6 | AJ11: =SUM(C11:N11) -> 10064339 | AK11: =SUM(O11:Z11) -> 11997576 | AL11: =SUM(AA11:AI11) -> 11066495
A12: Less: discounts, insurer short-pays & adjustments | B12: adjustments | C12: -3112.93 | D12: -4732.89 | E12: -4456.2 | F12: -5368.98 | G12: -5214.14 | H12: -3730.93 | I12: -3919.31 | J12: -7050.52 | K12: -6318.43 | L12: -4659.09 | M12: -5848.26 | N12: -7455.76 | O12: -7003.99 | P12: -5728.49 | Q12: -3822.35 | R12: -7025.26 | S12: -5024.58 | T12: -6709.7 | U12: -9388.76 | V12: -8121.62 | W12: -6005.21 | X12: -5200.75 | Y12: -5837.75 | Z12: -6626.11 | AA12: -15377.53 | AB12: -10945.71 | AC12: -7126.27 | AD12: -10302.45 | AE12: -7986.27 | AF12: -9013.52 | AG12: -8618.73 | AH12: -9706.23 | AI12: -8851.09 | AJ12: =SUM(C12:N12) -> -61867.44 | AK12: =SUM(O12:Z12) -> -76494.57 | AL12: =SUM(AA12:AI12) -> -87927.8
A13: Total net revenue | B13: net_rev | C13: =C11+C12 -> 770162.98 | D13: =D11+D12 -> 920715.7 | E13: =E11+E12 -> 808518.92 | F13: =F11+F12 -> 971247.11 | G13: =G11+G12 -> 1019857.6 | H13: =H11+H12 -> 650790.04 | I13: =I11+I12 -> 607610.74 | J13: =J11+J12 -> 695158.5 | ... AI13: =AI11+AI12 -> 1119754.5 | AJ13: =SUM(C13:N13) -> 10002471 | AK13: =SUM(O13:Z13) -> 11921081 | AL13: =SUM(AA13:AI13) -> 10978567
A14: Technician labour (wages, overtime & burden) | B14: labour | C14: -184665.84 | D14: -193295.91 | E14: -189178.51 | F14: -192140.21 | G14: -209583.72 | H14: -175669.4 | I14: -186308.75 | J14: -198237.28 | K14: -194715.88 | L14: -200562.87 | M14: -186447.4 | N14: -194208.37 | O14: -217523.26 | P14: -189598.76 | Q14: -213934.54 | R14: -200480.19 | S14: -262485.37 | T14: -246148.51 | U14: -274533.12 | V14: -276595.87 | W14: -265937.89 | X14: -274955.86 | Y14: -226633.95 | Z14: -273070.77 | AA14: -305536.52 | AB14: -264113.63 | AC14: -295322.5 | AD14: -281149.44 | AE14: -257540.24 | AF14: -294083.74 | AG14: -301668.59 | AH14: -292708.23 | AI14: -286020.55 | AJ14: =SUM(C14:N14) -> -2305014.1 | AK14: =SUM(O14:Z14) -> -2921898.1 | AL14: =SUM(AA14:AI14) -> -2578143.4
A15: Parts | B15: parts | C15: -293335.48 | D15: -333201.91 | E15: -295964.87 | F15: -373933.87 | G15: -392874.2 | H15: -232476.47 | I15: -209669.54 | J15: -228318.21 | K15: -327203.6 | L15: -381127.7 | M15: -373425.05 | N15: -277633.97 | O15: -334414.74 | P15: -314303.88 | Q15: -333132.75 | R15: -305328.15 | S15: -421390.49 | T15: -313567.03 | U15: -340506.54 | V15: -405551.86 | W15: -326934.78 | X15: -426972.28 | Y15: -434859.06 | Z15: -375548.4 | AA15: -560347.42 | AB15: -416923.86 | AC15: -416408.5 | AD15: -482027.65 | AE15: -467364.96 | AF15: -387410.92 | AG15: -370202.35 | AH15: -422239.01 | AI15: -377243.98 | AJ15: =SUM(C15:N15) -> -3719164.9 | AK15: =SUM(O15:Z15) -> -4332510 | AL15: =SUM(AA15:AI15) -> -3900168.6
A16: Paint & materials | B16: materials | C16: -19001.18 | D16: -25231.99 | E16: -21877.97 | F16: -23054.44 | G16: -23723.59 | H16: -14315.13 | I16: -15493.63 | J16: -17347.33 | K16: -24263.19 | L16: -20136.71 | M16: -21273.3 | N16: -19183.82 | O16: -27463.93 | P16: -23067.3 | Q16: -23952.09 | R16: -19269.34 | S16: -25390.7 | T16: -22742.32 | U16: -25635.19 | V16: -30607.72 | W16: -28328.72 | X16: -27421.32 | Y16: -20905.01 | Z16: -27047.79 | AA16: -40205.08 | AB16: -31989.93 | AC16: -34295.56 | AD16: -35082.49 | AE16: -25670.69 | AF16: -30151.59 | AG16: -30673.75 | AH16: -32071.04 | AI16: -30132.79 | AJ16: =SUM(C16:N16) -> -244902.28 | AK16: =SUM(O16:Z16) -> -301831.43 | AL16: =SUM(AA16:AI16) -> -290272.92
A17: Subcontractor costs (sublet repairs & towing) | B17: sublet | C17: -10636.54 | D17: -14436.04 | E17: -13037.97 | F17: -17280.48 | G17: -8712.2 | H17: -10328.04 | I17: -6089.55 | J17: -5076.08 | K17: -14997.07 | L17: -8279.17 | M17: -12930.21 | N17: -10563.67 | O17: -11604.39 | P17: -13501.79 | Q17: -11984.87 | R17: -9745.36 | S17: -19672.16 | T17: -15315.44 | U17: -10252.04 | V17: -11636 | W17: -14623.88 | X17: -16300.7 | Y17: -13427.54 | Z17: -16128.47 | AA17: -22299.46 | AB17: -15159.68 | AC17: -11174.66 | AD17: -12871.67 | AE17: -16060.85 | AF17: -11717.72 | AG17: -11469.74 | AH17: -11797.8 | AI17: -17473.1 | AJ17: =SUM(C17:N17) -> -132367.02 | AK17: =SUM(O17:Z17) -> -164192.64 | AL17: =SUM(AA17:AI17) -> -130024.68
A18: Warranty rework - parts & sublet | B18: warranty | C18: -522.03 | D18: -1923.35 | E18: -516.97 | F18: -466.67 | G18: -528.6 | H18: -44.57 | I18: -1205.22 | J18: -683.08 | K18: -887.68 | L18: -390.72 | M18: 0 | N18: -935.89 | O18: -792.55 | P18: -67.6 | Q18: -733.77 | R18: -255.74 | S18: -2163.01 | T18: 0 | U18: -18.42 | V18: -1428.25 | W18: -280.71 | X18: -826.23 | Y18: -504.32 | Z18: -519.24 | AA18: -1237.06 | AB18: -1283.49 | AC18: -516.41 | AD18: -561.99 | AE18: -339.28 | AF18: -258.18 | AG18: -1883.26 | AH18: -2815.51 | AI18: -1731.77 | AJ18: =SUM(C18:N18) -> -8104.78 | AK18: =SUM(O18:Z18) -> -7589.84 | AL18: =SUM(AA18:AI18) -> -10626.95
A19: Inventory adjustments & obsolescence | B19: inv_adj | C19: 0 | D19: 0 | E19: -298.1 | F19: 0 | G19: 0 | H19: 17.75 | I19: 0 | J19: 0 | K19: -303.34 | L19: 0 | M19: 0 | N19: -186.37 | O19: 0 | P19: 0 | Q19: -87.29 | R19: 0 | S19: 0 | T19: -223.77 | U19: 0 | V19: 0 | W19: -9.74 | X19: 0 | Y19: 0 | Z19: 19.04 | AA19: 0 | AB19: 0 | AC19: -201.31 | AD19: 0 | AE19: 0 | AF19: -9.45 | AG19: 0 | AH19: 0 | AI19: -165.51 | AJ19: =SUM(C19:N19) -> -770.06 | AK19: =SUM(O19:Z19) -> -301.76 | AL19: =SUM(AA19:AI19) -> -376.27
A20: Cost of sales | B20: cogs | C20: =C14+C15+C16+C17+C18+C19 -> -508161.07 | D20: =D14+D15+D16+D17+D18+D19 -> -568089.2 | E20: =E14+E15+E16+E17+E18+E19 -> -520874.39 | F20: =F14+F15+F16+F17+F18+F19 -> -606875.67 | G20: =G14+G15+G16+G17+G18+G19 -> -635422.31 | H20: =H14+H15+H16+H17+H18+H19 -> -432815.86 | I20: =I14+I15+I16+I17+I18+I19 -> -418766.69 | J20: =J14+J15+J16+J17+J18+J19 -> -449661.98 | ... AI20: =AI14+AI15+AI16+AI17+AI18+AI19 -> -712767.7 | AJ20: =SUM(C20:N20) -> -6410323.1 | AK20: =SUM(O20:Z20) -> -7728323.7 | AL20: =SUM(AA20:AI20) -> -6909612.9
A21: Gross profit | B21: gross_profit | C21: =C13+C20 -> 262001.91 | D21: =D13+D20 -> 352626.5 | E21: =E13+E20 -> 287644.53 | F21: =F13+F20 -> 364371.44 | G21: =G13+G20 -> 384435.33 | H21: =H13+H20 -> 217974.18 | I21: =I13+I20 -> 188844.05 | J21: =J13+J20 -> 245496.52 | ... AI21: =AI13+AI20 -> 406986.79 | AJ21: =SUM(C21:N21) -> 3592148.1 | AK21: =SUM(O21:Z21) -> 4192757.5 | AL21: =SUM(AA21:AI21) -> 4068954.6
A22: Staff compensation (branch & group) | B22: staff | C22: -100570 | D22: -100570 | E22: -100570 | F22: -100570 | G22: -100570 | H22: -100570 | I22: -100570 | J22: -100570 | K22: -100570 | L22: -100570 | M22: -100570 | N22: -100570 | O22: -109755.77 | P22: -109755.77 | Q22: -109755.77 | R22: -137107.42 | S22: -137107.42 | T22: -137107.42 | U22: -137107.42 | V22: -137107.42 | W22: -137107.42 | X22: -137107.42 | Y22: -137107.42 | Z22: -137107.42 | AA22: -141220.64 | AB22: -141220.64 | AC22: -141220.64 | AD22: -141220.64 | AE22: -141220.64 | AF22: -141220.64 | AG22: -141220.64 | AH22: -141220.64 | AI22: -141220.64 | AJ22: =SUM(C22:N22) -> -1206840 | AK22: =SUM(O22:Z22) -> -1563234.1 | AL22: =SUM(AA22:AI22) -> -1270985.8
A23: Occupancy (rent, CAM & property tax, utilities) | B23: occupancy | C23: -72843.66 | D23: -73435.17 | E23: -73704.37 | F23: -69047.85 | G23: -68945.94 | H23: -68738.92 | I23: -68827.72 | J23: -69209.81 | K23: -69109.39 | L23: -68862.37 | M23: -72766.65 | N23: -73342.49 | O23: -76061.55 | P23: -100421.52 | Q23: -101076.5 | R23: -95896.46 | S23: -97015.31 | T23: -96692.8 | U23: -96861.42 | V23: -97383.11 | W23: -96937.89 | X23: -96839.25 | Y23: -101975.37 | Z23: -102414.07 | AA23: -105820.42 | AB23: -105174.43 | AC23: -105652.09 | AD23: -99430.34 | AE23: -99612.97 | AF23: -99750.33 | AG23: -99710.23 | AH23: -99587.43 | AI23: -99717.89 | AJ23: =SUM(C23:N23) -> -848834.34 | AK23: =SUM(O23:Z23) -> -1159575.3 | AL23: =SUM(AA23:AI23) -> -914456.13
A24: Marketing & advertising | B24: marketing | C24: -10139.31 | D24: -8940.78 | E24: -8972.45 | F24: -10281.34 | G24: -9020.94 | H24: -9624.6 | I24: -9490.67 | J24: -9934.84 | K24: -9218.83 | L24: -8687.15 | M24: -9862.56 | N24: -9694.48 | O24: -9283.52 | P24: -9871.2 | Q24: -10739.22 | R24: -38866.32 | S24: -32504.94 | T24: -10155.81 | U24: -10676.64 | V24: -10246.8 | W24: -10048.28 | X24: -10536.58 | Y24: -10426.02 | Z24: -10106.62 | AA24: -9467.28 | AB24: -10332.55 | AC24: -9195.21 | AD24: -9282.52 | AE24: -9632.08 | AF24: -10935.11 | AG24: -10524.84 | AH24: -9524.83 | AI24: -9402.65 | AJ24: =SUM(C24:N24) -> -113867.95 | AK24: =SUM(O24:Z24) -> -173461.95 | AL24: =SUM(AA24:AI24) -> -88297.07
A25: General & administrative (insurance, professional, software, network, training) | B25: g_and_a | C25: -27452.59 | D25: -24646.12 | E25: -23979.55 | F25: -23522.46 | G25: -23745.35 | H25: -23950.88 | I25: -23433.37 | J25: -23866.01 | K25: -24614.13 | L25: -23605.95 | M25: -24585.99 | N25: -24416.1 | O25: -29447.16 | P25: -25999.34 | Q25: -25396.93 | R25: -25421.6 | S25: -28994.88 | T25: -29574.41 | U25: -29629.88 | V25: -29623.03 | W25: -29163.16 | X25: -29484.87 | Y25: -29614.29 | Z25: -28736.88 | AA25: -33477.72 | AB25: -29806.27 | AC25: -30245.15 | AD25: -30735.43 | AE25: -30152.99 | AF25: -30375.37 | AG25: -29841.06 | AH25: -30513.65 | AI25: -29548.44 | AJ25: =SUM(C25:N25) -> -291818.5 | AK25: =SUM(O25:Z25) -> -341086.43 | AL25: =SUM(AA25:AI25) -> -274696.08
A26: Shop operations (supplies, maintenance, courtesy vehicles, courier & waste, card fees) | B26: shop_ops | C26: -31810.43 | D26: -32712.36 | E26: -32935.65 | F26: -34119.14 | G26: -35071.66 | H26: -33106.69 | I26: -31995.86 | J26: -32743.54 | K26: -33832.07 | L26: -34551.74 | M26: -35944.58 | N26: -33345.47 | O26: -33656.05 | P26: -35056.66 | Q26: -35882.78 | R26: -36866.71 | S26: -47973.67 | T26: -47532.17 | U26: -45477.98 | V26: -48217.42 | W26: -45487.06 | X26: -48531.54 | Y26: -48546.26 | Z26: -45438.64 | AA26: -48446.41 | AB26: -45107.46 | AC26: -48818.61 | AD26: -52696.72 | AE26: -52560.22 | AF26: -48649.58 | AG26: -49827.24 | AH26: -48717.03 | AI26: -50572.91 | AJ26: =SUM(C26:N26) -> -402169.19 | AK26: =SUM(O26:Z26) -> -518666.94 | AL26: =SUM(AA26:AI26) -> -445396.18
A27: Operating expenses (before depreciation) | B27: opex | C27: =C22+C23+C24+C25+C26 -> -242815.99 | D27: =D22+D23+D24+D25+D26 -> -240304.43 | E27: =E22+E23+E24+E25+E26 -> -240162.02 | F27: =F22+F23+F24+F25+F26 -> -237540.79 | G27: =G22+G23+G24+G25+G26 -> -237353.89 | H27: =H22+H23+H24+H25+H26 -> -235991.09 | I27: =I22+I23+I24+I25+I26 -> -234317.62 | J27: =J22+J23+J24+J25+J26 -> -236324.2 | ... AI27: =AI22+AI23+AI24+AI25+AI26 -> -330462.53 | AJ27: =SUM(C27:N27) -> -2863530 | AK27: =SUM(O27:Z27) -> -3756024.7 | AL27: =SUM(AA27:AI27) -> -2993831.2
A28: EBITDA | B28: ebitda | C28: =C21+C27 -> 19185.92 | D28: =D21+D27 -> 112322.07 | E28: =E21+E27 -> 47482.51 | F28: =F21+F27 -> 126830.65 | G28: =G21+G27 -> 147081.44 | H28: =H21+H27 -> -18016.91 | I28: =I21+I27 -> -45473.57 | J28: =J21+J27 -> 9172.32 | ... AI28: =AI21+AI27 -> 76524.26 | AJ28: =SUM(C28:N28) -> 728618.12 | AK28: =SUM(O28:Z28) -> 436732.88 | AL28: =SUM(AA28:AI28) -> 1075123.3
A29: Depreciation | B29: da | C29: -15625 | D29: -15625 | E29: -15625 | F29: -15625 | G29: -15625 | H29: -15625 | I29: -15625 | J29: -15625 | K29: -15625 | L29: -16758.33 | M29: -16758.33 | N29: -16758.33 | O29: -16758.33 | P29: -16758.33 | Q29: -16758.33 | R29: -20175 | S29: -23016.67 | T29: -23016.67 | U29: -23016.67 | V29: -23016.67 | W29: -23016.67 | X29: -22016.67 | Y29: -22016.67 | Z29: -22016.67 | AA29: -22016.67 | AB29: -22016.67 | AC29: -22454.17 | AD29: -22454.17 | AE29: -22454.17 | AF29: -23245.84 | AG29: -23245.84 | AH29: -23245.84 | AI29: -23245.84 | AJ29: =SUM(C29:N29) -> -190899.99 | AK29: =SUM(O29:Z29) -> -251583.35 | AL29: =SUM(AA29:AI29) -> -204379.21
A30: Operating income (EBIT) | B30: ebit | C30: =C28+C29 -> 3560.92 | D30: =D28+D29 -> 96697.07 | E30: =E28+E29 -> 31857.51 | F30: =F28+F29 -> 111205.65 | G30: =G28+G29 -> 131456.44 | H30: =H28+H29 -> -33641.91 | I30: =I28+I29 -> -61098.57 | J30: =J28+J29 -> -6452.68 | ... AI30: =AI28+AI29 -> 53278.42 | AJ30: =SUM(C30:N30) -> 537718.13 | AK30: =SUM(O30:Z30) -> 185149.53 | AL30: =SUM(AA30:AI30) -> 870744.14
A31: Interest expense | B31: interest | C31: -3220 | D31: -3152.92 | E31: -3085.83 | F31: -3018.75 | G31: -2951.67 | H31: -2806.2 | I31: -2664.38 | J31: -2600.94 | K31: -2464.58 | L31: -2260.78 | M31: -2202.81 | N31: -2009.95 | O31: -1890 | P31: -1837.5 | Q31: -4423.02 | R31: -4372.34 | S31: -4276.67 | T31: -4180.99 | U31: -4085.31 | V31: -3989.64 | W31: -3756.98 | X31: -3531.09 | Y31: -3442.19 | Z31: -3353.28 | AA31: -3264.38 | AB31: -3175.47 | AC31: -3086.57 | AD31: -2997.66 | AE31: -2908.76 | AF31: -2819.84 | AG31: -2730.94 | AH31: -2642.03 | AI31: -2553.13 | AJ31: =SUM(C31:N31) -> -32438.81 | AK31: =SUM(O31:Z31) -> -43139.01 | AL31: =SUM(AA31:AI31) -> -26178.78
A32: Income before tax | B32: pbt | C32: =C30+C31 -> 340.92 | D32: =D30+D31 -> 93544.15 | E32: =E30+E31 -> 28771.68 | F32: =F30+F31 -> 108186.9 | G32: =G30+G31 -> 128504.77 | H32: =H30+H31 -> -36448.11 | I32: =I30+I31 -> -63762.95 | J32: =J30+J31 -> -9053.62 | ... AI32: =AI30+AI31 -> 50725.29 | AJ32: =SUM(C32:N32) -> 505279.32 | AK32: =SUM(O32:Z32) -> 142010.52 | AL32: =SUM(AA32:AI32) -> 844565.36
A33: Income taxes | B33: tax | C33: -37.5 | D33: -10289.86 | E33: -3164.88 | F33: -11900.56 | G33: -14135.53 | H33: 4009.3 | I33: 7013.92 | J33: 995.9 | K33: -7326.09 | L33: -11216.03 | M33: -16523.49 | N33: 6360.58 | O33: -7111.58 | P33: -3932.51 | Q33: -4144.91 | R33: 8092.25 | S33: -1373.16 | T33: 6710.44 | U33: 1759.47 | V33: -4784.26 | W33: -254.94 | X33: -8668.91 | Y33: -4818.84 | Z33: 2905.79 | AA33: -20304.98 | AB33: -4429.68 | AC33: -9224.66 | AD33: -20909.93 | AE33: -22662.61 | AF33: -14244.11 | AG33: -13281.29 | AH33: -17525.96 | AI33: -11666.81 | AJ33: =SUM(C33:N33) -> -56214.24 | AK33: =SUM(O33:Z33) -> -15621.16 | AL33: =SUM(AA33:AI33) -> -134250.03
A34: Net income | B34: net_income | C34: =C32+C33 -> 303.42 | D34: =D32+D33 -> 83254.29 | E34: =E32+E33 -> 25606.8 | F34: =F32+F33 -> 96286.34 | G34: =G32+G33 -> 114369.24 | H34: =H32+H33 -> -32438.81 | I34: =I32+I33 -> -56749.03 | J34: =J32+J33 -> -8057.72 | ... AI34: =AI32+AI33 -> 39058.48 | AJ34: =SUM(C34:N34) -> 449065.08 | AK34: =SUM(O34:Z34) -> 126389.36 | AL34: =SUM(AA34:AI34) -> 710315.33

Sheet Hist_BS
A1: ⚠ SIMULATED FINANCIAL INFORMATION - synthetic demonstration accounts of a fictional auto care group, not actual company records. Synthetic data generated for a VisiVault Analytics proof of concept (seed 20240103). Fictional auto care group.
A2: Historical balance sheets - month end (CAD)
A3: Monthly values from the general ledger; subtotal rows are live formulas. FY columns sum the months.
A5: Line | B5: Key | C5: 2024-01 | D5: 2024-02 | E5: 2024-03 | F5: 2024-04 | G5: 2024-05 | H5: 2024-06 | I5: 2024-07 | J5: 2024-08 | K5: 2024-09 | L5: 2024-10 | M5: 2024-11 | N5: 2024-12 | O5: 2025-01 | P5: 2025-02 | Q5: 2025-03 | R5: 2025-04 | S5: 2025-05 | T5: 2025-06 | U5: 2025-07 | V5: 2025-08 | W5: 2025-09 | X5: 2025-10 | Y5: 2025-11 | Z5: 2025-12 | AA5: 2026-01 | AB5: 2026-02 | AC5: 2026-03 | AD5: 2026-04 | AE5: 2026-05 | AF5: 2026-06 | AG5: 2026-07 | AH5: 2026-08 | AI5: 2026-09 | AJ5: FY2024 | AK5: FY2025 | AL5: YTD Sep-2026
A6: Cash | B6: cash | C6: 393720.32 | D6: 372419.59 | E6: 460110.57 | F6: 615172.88 | G6: 789119.67 | H6: 878504.97 | I6: 816261.3 | J6: 739018.59 | K6: 540268.22 | L6: 903226.19 | M6: 1083658.8 | N6: 846954.72 | O6: 691324.08 | P6: 729463.65 | Q6: 772353.79 | R6: 602823.51 | S6: 661000.43 | T6: 628697.79 | U6: 433184.42 | V6: 517582.44 | W6: 493927.6 | X6: 683095.21 | Y6: 864574.46 | Z6: 643396.37 | AA6: 510492.61 | AB6: 633407.78 | AC6: 930312.83 | AD6: 1079663.6 | AE6: 1191103.8 | AF6: 1342769.4 | AG6: 1129346 | AH6: 1300367.5 | AI6: 1390234 | AJ6: =N6 -> 846954.72 | AK6: =Z6 -> 643396.37 | AL6: =AI6 -> 1390234
A7: Insurer receivables (direct billing) | B7: ar_insurer | C7: 433861.48 | D7: 603581.3 | E7: 505108.03 | F7: 496841.21 | G7: 504740 | H7: 344074.43 | I7: 271127.44 | J7: 358310.92 | K7: 622300.62 | L7: 417249.48 | M7: 428467.66 | N7: 363070.71 | O7: 519555.24 | P7: 579289.91 | Q7: 590551.85 | R7: 411207.64 | S7: 501139.62 | T7: 410705.57 | U7: 547488.23 | V7: 616272.2 | W7: 633976.19 | X7: 585491.41 | Y7: 502017.27 | Z7: 515688.02 | AA7: 830843.66 | AB7: 720229.64 | AC7: 545393.95 | AD7: 623573.87 | AE7: 532091.1 | AF7: 468813.23 | AG7: 661457.7 | AH7: 647790.93 | AI7: 573560.54 | AJ7: =N7 -> 363070.71 | AK7: =Z7 -> 515688.02 | AL7: =AI7 -> 573560.54
A8: Card settlements & fleet receivables | B8: ar_other | C8: 76816.1 | D8: 53225.68 | E8: 35753.46 | F8: 76769.76 | G8: 71033.01 | H8: 30226.43 | I8: 61692.04 | J8: 62229.64 | K8: 31874.83 | L8: 62115.75 | M8: 67818.77 | N8: 51204.67 | O8: 61775.66 | P8: 71892 | Q8: 54330.92 | R8: 57030.39 | S8: 55786.75 | T8: 41892.16 | U8: 85027.46 | V8: 53009.85 | W8: 74454.67 | X8: 97419.16 | Y8: 74093.55 | Z8: 46911.99 | AA8: 70021.64 | AB8: 79759.33 | AC8: 104522.65 | AD8: 123012.25 | AE8: 79373.03 | AF8: 90501.98 | AG8: 81619.99 | AH8: 65088.72 | AI8: 110132.82 | AJ8: =N8 -> 51204.67 | AK8: =Z8 -> 46911.99 | AL8: =AI8 -> 110132.82
A9: Parts inventory (stocked & special-order) | B9: inventory | C9: 131712.53 | D9: 96802.61 | E9: 119127.68 | F9: 73924.71 | G9: 77659.23 | H9: 80462.68 | I9: 86222.52 | J9: 156841.96 | K9: 93018.15 | L9: 84217.9 | M9: 123511.08 | N9: 132711.05 | O9: 108395.28 | P9: 89677.64 | Q9: 94926.76 | R9: 113667.34 | S9: 111945.35 | T9: 113680.82 | U9: 118441.77 | V9: 127262.52 | W9: 103400.32 | X9: 135468.51 | Y9: 164727.08 | Z9: 253208.02 | AA9: 159559.79 | AB9: 143640.93 | AC9: 131204.64 | AD9: 113140.93 | AE9: 109224.85 | AF9: 152083.74 | AG9: 126816.81 | AH9: 130091.44 | AI9: 126398.77 | AJ9: =N9 -> 132711.05 | AK9: =Z9 -> 253208.02 | AL9: =AI9 -> 126398.77
A10: Paint & detailing materials | B10: materials | C10: 9219.79 | D10: 9814.85 | E10: 9117.25 | F10: 9516.73 | G10: 9222.49 | H10: 5586.78 | I10: 8171.94 | J10: 3839.27 | K10: 14243.84 | L10: 5223.29 | M10: 6409.11 | N10: 13477.03 | O10: 8975.83 | P10: 9892.63 | Q10: 12972.28 | R10: 6493.03 | S10: 9445.3 | T10: 14425.66 | U10: 7039.89 | V10: 10552.93 | W10: 12471.51 | X10: 6874.1 | Y10: 6840.3 | Z10: 19198.39 | AA10: 13289.17 | AB10: 13361.61 | AC10: 16296.93 | AD10: 16053.93 | AE10: 7849.79 | AF10: 14236.71 | AG10: 10889.36 | AH10: 18852.56 | AI10: 11736.47 | AJ10: =N10 -> 13477.03 | AK10: =Z10 -> 19198.39 | AL10: =AI10 -> 11736.47
A11: Work in progress - unbilled repair jobs (at cost) | B11: wip | C11: 145139.37 | D11: 125934.67 | E11: 101396.83 | F11: 150033.5 | G11: 69436.59 | H11: 48288.58 | I11: 64596.25 | J11: 125518.22 | K11: 119095.45 | L11: 108777.83 | M11: 107786.61 | N11: 115167.66 | O11: 87527.68 | P11: 113290.25 | Q11: 84190.62 | R11: 134003.79 | S11: 110064.14 | T11: 123413.89 | U11: 171056.65 | V11: 105185.77 | W11: 115310.77 | X11: 85917.28 | Y11: 171006.61 | Z11: 215178.21 | AA11: 162719.57 | AB11: 132913.06 | AC11: 113978.6 | AD11: 138398.07 | AE11: 107857.56 | AF11: 91617.59 | AG11: 149798.85 | AH11: 131430.98 | AI11: 115918.75 | AJ11: =N11 -> 115167.66 | AK11: =Z11 -> 215178.21 | AL11: =AI11 -> 115918.75
A12: Prepaid expenses | B12: prepaid | C12: 81400 | D12: 74000 | E12: 66600 | F12: 59200 | G12: 51800 | H12: 44400 | I12: 37000 | J12: 29600 | K12: 22200 | L12: 14800 | M12: 7400 | N12: 0 | O12: 92988.4 | P12: 85366.4 | Q12: 77744.4 | R12: 70122.4 | S12: 61357.1 | T12: 52591.8 | U12: 43826.5 | V12: 35061.2 | W12: 26295.9 | X12: 17530.6 | Y12: 8765.3 | Z12: 0 | AA12: 99310.86 | AB12: 90282.6 | AC12: 81254.34 | AD12: 72226.08 | AE12: 63197.82 | AF12: 54169.56 | AG12: 45141.3 | AH12: 36113.04 | AI12: 27084.78 | AJ12: =N12 -> 0 | AK12: =Z12 -> 0 | AL12: =AI12 -> 27084.78
A13: GST recoverable | B13: gst_rec | C13: 0 | D13: 0 | E13: 0 | F13: 0 | G13: 0 | H13: 0 | I13: 0 | J13: 0 | K13: 0 | L13: 0 | M13: 0 | N13: 0 | O13: 0 | P13: 0 | Q13: 0 | R13: 773.09 | S13: 0 | T13: 0 | U13: 0 | V13: 0 | W13: 0 | X13: 0 | Y13: 0 | Z13: 0 | AA13: 0 | AB13: 0 | AC13: 0 | AD13: 0 | AE13: 0 | AF13: 0 | AG13: 0 | AH13: 0 | AI13: 0 | AJ13: =N13 -> 0 | AK13: =Z13 -> 0 | AL13: =AI13 -> 0
A14: Total current assets | B14: current_assets | C14: =C6+C7+C8+C9+C10+C11+C12+C13 -> 1271869.6 | D14: =D6+D7+D8+D9+D10+D11+D12+D13 -> 1335778.7 | E14: =E6+E7+E8+E9+E10+E11+E12+E13 -> 1297213.8 | F14: =F6+F7+F8+F9+F10+F11+F12+F13 -> 1481458.8 | G14: =G6+G7+G8+G9+G10+G11+G12+G13 -> 1573011 | H14: =H6+H7+H8+H9+H10+H11+H12+H13 -> 1431543.9 | I14: =I6+I7+I8+I9+I10+I11+I12+I13 -> 1345071.5 | J14: =J6+J7+J8+J9+J10+J11+J12+J13 -> 1475358.6 | ... AI14: =AI6+AI7+AI8+AI9+AI10+AI11+AI12+AI13 -> 2355066.1 | AJ14: =N14 -> 1522585.8 | AK14: =Z14 -> 1693581 | AL14: =AI14 -> 2355066.1
A15: Fixed assets at cost | B15: ppe_gross | C15: 2070000 | D15: 2070000 | E15: 2070000 | F15: 2070000 | G15: 2070000 | H15: 2070000 | I15: 2070000 | J15: 2070000 | K15: 2138000 | L15: 2138000 | M15: 2138000 | N15: 2138000 | O15: 2138000 | P15: 2138000 | Q15: 2548000 | R15: 2811000 | S15: 2811000 | T15: 2811000 | U15: 2811000 | V15: 2811000 | W15: 2811000 | X15: 2811000 | Y15: 2811000 | Z15: 2811000 | AA15: 2811000 | AB15: 2853000 | AC15: 2853000 | AD15: 2853000 | AE15: 2948000 | AF15: 2948000 | AG15: 2948000 | AH15: 2948000 | AI15: 2948000 | AJ15: =N15 -> 2138000 | AK15: =Z15 -> 2811000 | AL15: =AI15 -> 2948000
A16: Accumulated depreciation | B16: acc_dep | C16: -974472.49 | D16: -990097.49 | E16: -1005722.5 | F16: -1021347.5 | G16: -1036972.5 | H16: -1052597.5 | I16: -1068222.5 | J16: -1083847.5 | K16: -1099472.5 | L16: -1116230.8 | M16: -1132989.1 | N16: -1149747.5 | O16: -1166505.8 | P16: -1183264.1 | Q16: -1200022.5 | R16: -1220197.5 | S16: -1243214.1 | T16: -1266230.8 | U16: -1289247.5 | V16: -1312264.1 | W16: -1335280.8 | X16: -1357297.5 | Y16: -1379314.2 | Z16: -1401330.8 | AA16: -1423347.5 | AB16: -1445364.2 | AC16: -1467818.3 | AD16: -1490272.5 | AE16: -1512726.7 | AF16: -1535972.5 | AG16: -1559218.4 | AH16: -1582464.2 | AI16: -1605710 | AJ16: =N16 -> -1149747.5 | AK16: =Z16 -> -1401330.8 | AL16: =AI16 -> -1605710
A17: Net fixed assets | B17: ppe_net | C17: =C15+C16 -> 1095527.5 | D17: =D15+D16 -> 1079902.5 | E17: =E15+E16 -> 1064277.5 | F17: =F15+F16 -> 1048652.5 | G17: =G15+G16 -> 1033027.5 | H17: =H15+H16 -> 1017402.5 | I17: =I15+I16 -> 1001777.5 | J17: =J15+J16 -> 986152.51 | ... AI17: =AI15+AI16 -> 1342290 | AJ17: =N17 -> 988252.52 | AK17: =Z17 -> 1409669.2 | AL17: =AI17 -> 1342290
A18: TOTAL ASSETS | B18: total_assets | C18: =C14+C17 -> 2367397.1 | D18: =D14+D17 -> 2415681.2 | E18: =E14+E17 -> 2361491.3 | F18: =F14+F17 -> 2530111.3 | G18: =G14+G17 -> 2606038.5 | H18: =H14+H17 -> 2448946.4 | I18: =I14+I17 -> 2346849 | J18: =J14+J17 -> 2461511.1 | ... AI18: =AI14+AI17 -> 3697356.1 | AJ18: =N18 -> 2510838.4 | AK18: =Z18 -> 3103250.2 | AL18: =AI18 -> 3697356.1
A19: Accounts payable (suppliers, sublet & vendors) | B19: ap | C19: 490370.93 | D19: 435380.02 | E19: 408607.24 | F19: 500878.97 | G19: 431081.81 | H19: 316685.62 | I19: 332793.81 | J19: 445640.71 | K19: 395109.21 | L19: 451003.72 | M19: 545947.26 | N19: 424657.37 | O19: 418392.33 | P19: 475571.37 | Q19: 443685.67 | R19: 517781.45 | S19: 564049.34 | T19: 477554.57 | U19: 532594.44 | V19: 501103.64 | W19: 464832.41 | X19: 575994.04 | Y19: 703732.34 | Z19: 639637.88 | AA19: 610694.5 | AB19: 568840.58 | AC19: 552207.87 | AD19: 673659.01 | AE19: 572740.67 | AF19: 584576.34 | AG19: 560274.95 | AH19: 580697.2 | AI19: 526655.94 | AJ19: =N19 -> 424657.37 | AK19: =Z19 -> 639637.88 | AL19: =AI19 -> 526655.94
A20: Accrued payroll | B20: accrued | C20: 150143.15 | D20: 145168.34 | E20: 142336.91 | F20: 150553.24 | G20: 149610.73 | H20: 137532.62 | I20: 143783.69 | J20: 153301.58 | K20: 146839.55 | L20: 151006.51 | M20: 143394.72 | N20: 147092.05 | O20: 161740.08 | P20: 150990.22 | Q20: 161320.69 | R20: 171142.4 | S20: 197321.89 | T20: 195120.66 | U20: 206390.83 | V20: 203528.52 | W20: 202537.98 | X20: 202427.34 | Y20: 187868.53 | Z20: 209720.11 | AA20: 218477.03 | AB20: 199435.62 | AC20: 221103.3 | AD20: 208991.81 | AE20: 199642.31 | AF20: 216983.13 | AG20: 223795.3 | AH20: 216752.45 | AI20: 211225.52 | AJ20: =N20 -> 147092.05 | AK20: =Z20 -> 209720.11 | AL20: =AI20 -> 211225.52
A21: GST payable | B21: gst_pay | C21: 12373.19 | D21: 35828.87 | E21: 53221.52 | F21: 21916.53 | G21: 48828.63 | H21: 63408.92 | I21: 11465.23 | J21: 21566.17 | K21: 40726.4 | L21: 23302.03 | M21: 43117.97 | N21: 56890.71 | O21: 23805.03 | P21: 41947.69 | Q21: 42226 | R21: 0 | S21: 22920.12 | T21: 40522.49 | U21: 18963.36 | V21: 47053.32 | W21: 70140.86 | X21: 26474.25 | Y21: 43948.71 | Z21: 58397.67 | AA21: 40883.01 | AB21: 65099.53 | AC21: 94989.95 | AD21: 32460.76 | AE21: 57000.28 | AF21: 82391.3 | AG21: 26017.75 | AH21: 54107.9 | AI21: 81285.92 | AJ21: =N21 -> 56890.71 | AK21: =Z21 -> 58397.67 | AL21: =AI21 -> 81285.92
A22: Income taxes payable | B22: tax_payable | C22: 62037.5 | D22: 72327.36 | E22: 13492.24 | F22: 25392.8 | G22: 39528.33 | H22: 35519.03 | I22: 28505.11 | J22: 27509.21 | K22: 34835.3 | L22: 46051.33 | M22: 62574.82 | N22: 56214.24 | O22: 63325.82 | P22: 67258.33 | Q22: 15189 | R22: 7096.75 | S22: 8469.91 | T22: 1759.47 | U22: 0 | V22: 4784.26 | W22: 5039.2 | X22: 13708.11 | Y22: 18526.95 | Z22: 15621.16 | AA22: 35926.14 | AB22: 40355.82 | AC22: 33959.32 | AD22: 54869.25 | AE22: 77531.86 | AF22: 91775.97 | AG22: 105057.26 | AH22: 122583.22 | AI22: 134250.03 | AJ22: =N22 -> 56214.24 | AK22: =Z22 -> 15621.16 | AL22: =AI22 -> 134250.03
A23: Revolving line of credit | B23: revolver | C23: 0 | D23: 0 | E23: 0 | F23: 0 | G23: 0 | H23: 0 | I23: 0 | J23: 0 | K23: 0 | L23: 0 | M23: 0 | N23: 0 | O23: 0 | P23: 0 | Q23: 0 | R23: 0 | S23: 0 | T23: 0 | U23: 0 | V23: 0 | W23: 0 | X23: 0 | Y23: 0 | Z23: 0 | AA23: 0 | AB23: 0 | AC23: 0 | AD23: 0 | AE23: 0 | AF23: 0 | AG23: 0 | AH23: 0 | AI23: 0 | AJ23: =N23 -> 0 | AK23: =Z23 -> 0 | AL23: =AI23 -> 0
A24: Current portion of term loans | B24: term_current | C24: 105000 | D24: 105000 | E24: 105000 | F24: 112500 | G24: 120000 | H24: 127500 | I24: 135000 | J24: 142500 | K24: 150000 | L24: 157500 | M24: 165000 | N24: 172500 | O24: 180000 | P24: 187500 | Q24: 195000 | R24: 195000 | S24: 195000 | T24: 195000 | U24: 195000 | V24: 195000 | W24: 195000 | X24: 195000 | Y24: 195000 | Z24: 195000 | AA24: 195000 | AB24: 195000 | AC24: 195000 | AD24: 195000 | AE24: 195000 | AF24: 195000 | AG24: 195000 | AH24: 195000 | AI24: 195000 | AJ24: =N24 -> 172500 | AK24: =Z24 -> 195000 | AL24: =AI24 -> 195000
A25: Total current liabilities | B25: current_liabilities | C25: =C19+C20+C21+C22+C23+C24 -> 819924.77 | D25: =D19+D20+D21+D22+D23+D24 -> 793704.59 | E25: =E19+E20+E21+E22+E23+E24 -> 722657.91 | F25: =F19+F20+F21+F22+F23+F24 -> 811241.54 | G25: =G19+G20+G21+G22+G23+G24 -> 789049.5 | H25: =H19+H20+H21+H22+H23+H24 -> 680646.19 | I25: =I19+I20+I21+I22+I23+I24 -> 651547.84 | J25: =J19+J20+J21+J22+J23+J24 -> 790517.67 | ... AI25: =AI19+AI20+AI21+AI22+AI23+AI24 -> 1148417.4 | AJ25: =N25 -> 857354.37 | AK25: =Z25 -> 1118376.8 | AL25: =AI25 -> 1148417.4
A26: Term loans (non-current) | B26: term_lt | C26: 306250 | D26: 297500 | E26: 288750 | F26: 272500 | G26: 256250 | H26: 240000 | I26: 223750 | J26: 207500 | K26: 191250 | L26: 175000 | M26: 158750 | N26: 142500 | O26: 126250 | P26: 110000 | Q26: 543750 | R26: 527500 | S26: 511250 | T26: 495000 | U26: 478750 | V26: 462500 | W26: 446250 | X26: 430000 | Y26: 413750 | Z26: 397500 | AA26: 381250 | AB26: 365000 | AC26: 348750 | AD26: 332500 | AE26: 316250 | AF26: 300000 | AG26: 283750 | AH26: 267500 | AI26: 251250 | AJ26: =N26 -> 142500 | AK26: =Z26 -> 397500 | AL26: =AI26 -> 251250
A27: TOTAL LIABILITIES | B27: total_liabilities | C27: =C25+C26 -> 1126174.8 | D27: =D25+D26 -> 1091204.6 | E27: =E25+E26 -> 1011407.9 | F27: =F25+F26 -> 1083741.5 | G27: =G25+G26 -> 1045299.5 | H27: =H25+H26 -> 920646.19 | I27: =I25+I26 -> 875297.84 | J27: =J25+J26 -> 998017.67 | ... AI27: =AI25+AI26 -> 1399667.4 | AJ27: =N27 -> 999854.37 | AK27: =Z27 -> 1515876.8 | AL27: =AI27 -> 1399667.4
A28: Share capital | B28: share_capital | C28: 200000 | D28: 200000 | E28: 200000 | F28: 200000 | G28: 200000 | H28: 200000 | I28: 200000 | J28: 200000 | K28: 200000 | L28: 200000 | M28: 200000 | N28: 200000 | O28: 200000 | P28: 200000 | Q28: 200000 | R28: 200000 | S28: 200000 | T28: 200000 | U28: 200000 | V28: 200000 | W28: 200000 | X28: 200000 | Y28: 200000 | Z28: 200000 | AA28: 200000 | AB28: 200000 | AC28: 200000 | AD28: 200000 | AE28: 200000 | AF28: 200000 | AG28: 200000 | AH28: 200000 | AI28: 200000 | AJ28: =N28 -> 200000 | AK28: =Z28 -> 200000 | AL28: =AI28 -> 200000
A29: Retained earnings | B29: retained | C29: 1040918.9 | D29: 1040918.9 | E29: 1040918.9 | F29: 1040918.9 | G29: 1040918.9 | H29: 1040918.9 | I29: 1040918.9 | J29: 1040918.9 | K29: 1040918.9 | L29: 1040918.9 | M29: 1040918.9 | N29: 1310984 | O29: 1310984 | P29: 1310984 | Q29: 1310984 | R29: 1310984 | S29: 1310984 | T29: 1310984 | U29: 1310984 | V29: 1310984 | W29: 1310984 | X29: 1310984 | Y29: 1310984 | Z29: 1387373.4 | AA29: 1387373.4 | AB29: 1387373.4 | AC29: 1387373.4 | AD29: 1387373.4 | AE29: 1387373.4 | AF29: 1387373.4 | AG29: 1387373.4 | AH29: 1387373.4 | AI29: 1387373.4 | AJ29: =N29 -> 1310984 | AK29: =Z29 -> 1387373.4 | AL29: =AI29 -> 1387373.4
A30: Current-year earnings | B30: cpe | C30: 303.42 | D30: 83557.71 | E30: 109164.51 | F30: 205450.85 | G30: 319820.09 | H30: 287381.28 | I30: 230632.25 | J30: 222574.53 | K30: 281849.25 | L30: 372597.12 | M30: 470359.18 | N30: 0 | O30: 57539.11 | P30: 89356.74 | Q30: 122892.8 | R30: 57419.13 | S30: 68529.3 | T30: 14235.7 | U30: -14865.18 | V30: 38709.03 | W30: 40771.7 | X30: 110911.05 | Y30: 149899.89 | Z30: 0 | AA30: 164285.77 | AB30: 200125.88 | AC30: 274761.81 | AD30: 443942.09 | AE30: 520432.76 | AF30: 568119.55 | AG30: 612583.01 | AH30: 671256.85 | AI30: 710315.33 | AJ30: =N30 -> 0 | AK30: =Z30 -> 0 | AL30: =AI30 -> 710315.33
A31: TOTAL EQUITY | B31: total_equity | C31: =C28+C29+C30 -> 1241222.3 | D31: =D28+D29+D30 -> 1324476.6 | E31: =E28+E29+E30 -> 1350083.4 | F31: =F28+F29+F30 -> 1446369.8 | G31: =G28+G29+G30 -> 1560739 | H31: =H28+H29+H30 -> 1528300.2 | I31: =I28+I29+I30 -> 1471551.2 | J31: =J28+J29+J30 -> 1463493.4 | ... AI31: =AI28+AI29+AI30 -> 2297688.7 | AJ31: =N31 -> 1510984 | AK31: =Z31 -> 1587373.4 | AL31: =AI31 -> 2297688.7
A32: TOTAL LIABILITIES AND EQUITY | B32: total_le | C32: =C27+C31 -> 2367397.1 | D32: =D27+D31 -> 2415681.2 | E32: =E27+E31 -> 2361491.3 | F32: =F27+F31 -> 2530111.3 | G32: =G27+G31 -> 2606038.5 | H32: =H27+H31 -> 2448946.4 | I32: =I27+I31 -> 2346849 | J32: =J27+J31 -> 2461511.1 | ... AI32: =AI27+AI31 -> 3697356.1 | AJ32: =N32 -> 2510838.4 | AK32: =Z32 -> 3103250.2 | AL32: =AI32 -> 3697356.1
A33: Check: assets - liabilities - equity | B33: check | C33: =ROUND(C18-C32,2) -> 0 | D33: =ROUND(D18-D32,2) -> 0 | E33: =ROUND(E18-E32,2) -> 0 | F33: =ROUND(F18-F32,2) -> 0 | G33: =ROUND(G18-G32,2) -> 0 | H33: =ROUND(H18-H32,2) -> 0 | I33: =ROUND(I18-I32,2) -> 0 | J33: =ROUND(J18-J32,2) -> 0 | ... AI33: =ROUND(AI18-AI32,2) -> 0 | AJ33: =N33 -> 0 | AK33: =Z33 -> 0 | AL33: =AI33 -> 0

Sheet Hist_CF
A1: ⚠ SIMULATED FINANCIAL INFORMATION - synthetic demonstration accounts of a fictional auto care group, not actual company records. Synthetic data generated for a VisiVault Analytics proof of concept (seed 20240103). Fictional auto care group.
A2: Historical cash flow statements - indirect method (CAD)
A3: Monthly values from the general ledger; subtotal rows are live formulas. FY columns sum the months.
A5: Line | B5: Key | C5: 2024-01 | D5: 2024-02 | E5: 2024-03 | F5: 2024-04 | G5: 2024-05 | H5: 2024-06 | I5: 2024-07 | J5: 2024-08 | K5: 2024-09 | L5: 2024-10 | M5: 2024-11 | N5: 2024-12 | O5: 2025-01 | P5: 2025-02 | Q5: 2025-03 | R5: 2025-04 | S5: 2025-05 | T5: 2025-06 | U5: 2025-07 | V5: 2025-08 | W5: 2025-09 | X5: 2025-10 | Y5: 2025-11 | Z5: 2025-12 | AA5: 2026-01 | AB5: 2026-02 | AC5: 2026-03 | AD5: 2026-04 | AE5: 2026-05 | AF5: 2026-06 | AG5: 2026-07 | AH5: 2026-08 | AI5: 2026-09 | AJ5: FY2024 | AK5: FY2025 | AL5: YTD Sep-2026
A6: Net income | B6: net_income | C6: 303.42 | D6: 83254.29 | E6: 25606.8 | F6: 96286.34 | G6: 114369.24 | H6: -32438.81 | I6: -56749.03 | J6: -8057.72 | K6: 59274.72 | L6: 90747.87 | M6: 97762.06 | N6: -21294.1 | O6: 57539.11 | P6: 31817.63 | Q6: 33536.06 | R6: -65473.67 | S6: 11110.17 | T6: -54293.6 | U6: -29100.88 | V6: 53574.21 | W6: 2062.67 | X6: 70139.35 | Y6: 38988.84 | Z6: -23510.53 | AA6: 164285.77 | AB6: 35840.11 | AC6: 74635.93 | AD6: 169180.28 | AE6: 76490.67 | AF6: 47686.79 | AG6: 44463.46 | AH6: 58673.84 | AI6: 39058.48 | AJ6: =SUM(C6:N6) -> 449065.08 | AK6: =SUM(O6:Z6) -> 126389.36 | AL6: =SUM(AA6:AI6) -> 710315.33
A7: Depreciation | B7: da | C7: 15625 | D7: 15625 | E7: 15625 | F7: 15625 | G7: 15625 | H7: 15625 | I7: 15625 | J7: 15625 | K7: 15625 | L7: 16758.33 | M7: 16758.33 | N7: 16758.33 | O7: 16758.33 | P7: 16758.33 | Q7: 16758.33 | R7: 20175 | S7: 23016.67 | T7: 23016.67 | U7: 23016.67 | V7: 23016.67 | W7: 23016.67 | X7: 22016.67 | Y7: 22016.67 | Z7: 22016.67 | AA7: 22016.67 | AB7: 22016.67 | AC7: 22454.17 | AD7: 22454.17 | AE7: 22454.17 | AF7: 23245.84 | AG7: 23245.84 | AH7: 23245.84 | AI7: 23245.84 | AJ7: =SUM(C7:N7) -> 190899.99 | AK7: =SUM(O7:Z7) -> 251583.35 | AL7: =SUM(AA7:AI7) -> 204379.21
A8: (Increase) decrease in receivables (insurer, fleet, card) | B8: d_ar | C8: 15841.64 | D8: -146129.4 | E8: 115945.49 | F8: -32749.48 | G8: -2162.04 | H8: 201472.15 | I8: 41481.38 | J8: -87721.08 | K8: -233634.89 | L8: 174810.22 | M8: -16921.2 | N8: 82011.05 | O8: -167055.52 | P8: -69851.01 | Q8: 6299.14 | R8: 176644.74 | S8: -88688.34 | T8: 104328.64 | U8: -179917.96 | V8: -36766.36 | W8: -39148.81 | X8: 25520.29 | Y8: 106799.75 | Z8: 13510.81 | AA8: -338265.29 | AB8: 100876.33 | AC8: 150072.37 | AD8: -96669.52 | AE8: 135121.99 | AF8: 52148.92 | AG8: -183762.48 | AH8: 30198.04 | AI8: 29186.29 | AJ8: =SUM(C8:N8) -> 112243.84 | AK8: =SUM(O8:Z8) -> -148324.63 | AL8: =SUM(AA8:AI8) -> -121093.35
A9: (Increase) decrease in parts & materials inventory | B9: d_inv | C9: 2831.34 | D9: 34314.86 | E9: -21627.47 | F9: 44803.49 | G9: -3440.28 | H9: 832.26 | I9: -8345 | J9: -66286.77 | K9: 53419.24 | L9: 17820.8 | M9: -40479 | N9: -16267.89 | O9: 28816.97 | P9: 17800.84 | Q9: -8328.77 | R9: -12261.33 | S9: -1230.28 | T9: -6715.83 | U9: 2624.82 | V9: -12333.79 | W9: 21943.62 | X9: -26470.78 | Y9: -29224.77 | Z9: -100839.03 | AA9: 99557.45 | AB9: 15846.42 | AC9: 9500.97 | AD9: 18306.71 | AE9: 12120.22 | AF9: -49245.81 | AG9: 28614.28 | AH9: -11237.83 | AI9: 10808.76 | AJ9: =SUM(C9:N9) -> -2424.42 | AK9: =SUM(O9:Z9) -> -126218.33 | AL9: =SUM(AA9:AI9) -> 134271.17
A10: (Increase) decrease in work in progress | B10: d_wip | C10: -87988.38 | D10: 19204.7 | E10: 24537.84 | F10: -48636.67 | G10: 80596.91 | H10: 21148.01 | I10: -16307.67 | J10: -60921.97 | K10: 6422.77 | L10: 10317.62 | M10: 991.22 | N10: -7381.05 | O10: 27639.98 | P10: -25762.57 | Q10: 29099.63 | R10: -49813.17 | S10: 23939.65 | T10: -13349.75 | U10: -47642.76 | V10: 65870.88 | W10: -10125 | X10: 29393.49 | Y10: -85089.33 | Z10: -44171.6 | AA10: 52458.64 | AB10: 29806.51 | AC10: 18934.46 | AD10: -24419.47 | AE10: 30540.51 | AF10: 16239.97 | AG10: -58181.26 | AH10: 18367.87 | AI10: 15512.23 | AJ10: =SUM(C10:N10) -> -58016.67 | AK10: =SUM(O10:Z10) -> -100010.55 | AL10: =SUM(AA10:AI10) -> 99259.46
A11: Increase (decrease) in supplier & vendor payables | B11: d_ap | C11: 124092.68 | D11: -54990.91 | E11: -26772.78 | F11: 92271.73 | G11: -69797.16 | H11: -114396.19 | I11: 16108.19 | J11: 112846.9 | K11: -50531.5 | L11: 55894.51 | M11: 94943.54 | N11: -121289.89 | O11: -6265.04 | P11: 57179.04 | Q11: -31885.7 | R11: 74095.78 | S11: 46267.89 | T11: -86494.77 | U11: 55039.87 | V11: -31490.8 | W11: -36271.23 | X11: 111161.63 | Y11: 127738.3 | Z11: -64094.46 | AA11: -28943.38 | AB11: -41853.92 | AC11: -16632.71 | AD11: 121451.14 | AE11: -100918.34 | AF11: 11835.67 | AG11: -24301.39 | AH11: 20422.25 | AI11: -54041.26 | AJ11: =SUM(C11:N11) -> 58379.12 | AK11: =SUM(O11:Z11) -> 214980.51 | AL11: =SUM(AA11:AI11) -> -112981.94
A12: Other working capital (prepaid, accrued payroll, GST, tax) | B12: d_other | C12: -88235.38 | D12: 36170.73 | E12: -36873.9 | F12: -3788.1 | G12: 47505.12 | H12: 5892.88 | I12: -45306.54 | J12: 26022.93 | K12: 27424.29 | L12: 5358.62 | M12: 36127.64 | N12: 18509.49 | O12: -104314.47 | P12: 18947.31 | Q12: -33838.55 | R12: -33647.63 | S12: 60011.16 | T12: 17456 | U12: -3283.13 | V12: 38777.21 | W12: 31117.24 | X12: -26343.04 | Y12: 16499.79 | Z12: 42160.05 | AA12: -87763.62 | AB12: 18633.05 | AC12: 54189.86 | AD12: -44702.49 | AE12: 46880.89 | AF12: 66004.21 | AG12: -27251.83 | AH12: 47601.52 | AI12: 42346.16 | AJ12: =SUM(C12:N12) -> 28807.78 | AK12: =SUM(O12:Z12) -> 23541.94 | AL12: =SUM(AA12:AI12) -> 115937.75
A13: Net cash from operating activities | B13: cfo | C13: =C6+C7+C8+C9+C10+C11+C12 -> -17529.68 | D13: =D6+D7+D8+D9+D10+D11+D12 -> -12550.73 | E13: =E6+E7+E8+E9+E10+E11+E12 -> 96440.98 | F13: =F6+F7+F8+F9+F10+F11+F12 -> 163812.31 | G13: =G6+G7+G8+G9+G10+G11+G12 -> 182696.79 | H13: =H6+H7+H8+H9+H10+H11+H12 -> 98135.3 | I13: =I6+I7+I8+I9+I10+I11+I12 -> -53493.67 | J13: =J6+J7+J8+J9+J10+J11+J12 -> -68492.71 | ... AI13: =AI6+AI7+AI8+AI9+AI10+AI11+AI12 -> 106116.5 | AJ13: =SUM(C13:N13) -> 778954.72 | AK13: =SUM(O13:Z13) -> 241941.65 | AL13: =SUM(AA13:AI13) -> 1030087.6
A14: Capital expenditures | B14: capex | C14: 0 | D14: 0 | E14: 0 | F14: 0 | G14: 0 | H14: 0 | I14: 0 | J14: 0 | K14: -68000 | L14: 0 | M14: 0 | N14: 0 | O14: 0 | P14: 0 | Q14: -410000 | R14: -263000 | S14: 0 | T14: 0 | U14: 0 | V14: 0 | W14: 0 | X14: 0 | Y14: 0 | Z14: 0 | AA14: 0 | AB14: -42000 | AC14: 0 | AD14: 0 | AE14: -95000 | AF14: 0 | AG14: 0 | AH14: 0 | AI14: 0 | AJ14: =SUM(C14:N14) -> -68000 | AK14: =SUM(O14:Z14) -> -673000 | AL14: =SUM(AA14:AI14) -> -137000
A15: Net cash used in investing activities | B15: cfi | C15: =C14 -> 0 | D15: =D14 -> 0 | E15: =E14 -> 0 | F15: =F14 -> 0 | G15: =G14 -> 0 | H15: =H14 -> 0 | I15: =I14 -> 0 | J15: =J14 -> 0 | ... AI15: =AI14 -> 0 | AJ15: =SUM(C15:N15) -> -68000 | AK15: =SUM(O15:Z15) -> -673000 | AL15: =SUM(AA15:AI15) -> -137000
A16: Borrowings (equipment loan & revolver draws) | B16: borrowings | C16: 0 | D16: 0 | E16: 0 | F16: 0 | G16: 0 | H16: 0 | I16: 0 | J16: 0 | K16: 0 | L16: 0 | M16: 0 | N16: 0 | O16: 0 | P16: 0 | Q16: 450000 | R16: 0 | S16: 0 | T16: 0 | U16: 0 | V16: 0 | W16: 0 | X16: 0 | Y16: 0 | Z16: 0 | AA16: 0 | AB16: 0 | AC16: 0 | AD16: 0 | AE16: 0 | AF16: 0 | AG16: 0 | AH16: 0 | AI16: 0 | AJ16: =SUM(C16:N16) -> 0 | AK16: =SUM(O16:Z16) -> 450000 | AL16: =SUM(AA16:AI16) -> 0
A17: Debt repayments (loan principal & revolver) | B17: repayments | C17: -8750 | D17: -8750 | E17: -8750 | F17: -8750 | G17: -8750 | H17: -8750 | I17: -8750 | J17: -8750 | K17: -8750 | L17: -8750 | M17: -8750 | N17: -8750 | O17: -8750 | P17: -8750 | Q17: -8750 | R17: -16250 | S17: -16250 | T17: -16250 | U17: -16250 | V17: -16250 | W17: -16250 | X17: -16250 | Y17: -16250 | Z17: -16250 | AA17: -16250 | AB17: -16250 | AC17: -16250 | AD17: -16250 | AE17: -16250 | AF17: -16250 | AG17: -16250 | AH17: -16250 | AI17: -16250 | AJ17: =SUM(C17:N17) -> -105000 | AK17: =SUM(O17:Z17) -> -172500 | AL17: =SUM(AA17:AI17) -> -146250
A18: Dividends paid | B18: dividends | C18: 0 | D18: 0 | E18: 0 | F18: 0 | G18: 0 | H18: 0 | I18: 0 | J18: 0 | K18: 0 | L18: 0 | M18: 0 | N18: -179000 | O18: 0 | P18: 0 | Q18: 0 | R18: 0 | S18: 0 | T18: 0 | U18: 0 | V18: 0 | W18: 0 | X18: 0 | Y18: 0 | Z18: -50000 | AA18: 0 | AB18: 0 | AC18: 0 | AD18: 0 | AE18: 0 | AF18: 0 | AG18: 0 | AH18: 0 | AI18: 0 | AJ18: =SUM(C18:N18) -> -179000 | AK18: =SUM(O18:Z18) -> -50000 | AL18: =SUM(AA18:AI18) -> 0
A19: Net cash from (used in) financing activities | B19: cff | C19: =C16+C17+C18 -> -8750 | D19: =D16+D17+D18 -> -8750 | E19: =E16+E17+E18 -> -8750 | F19: =F16+F17+F18 -> -8750 | G19: =G16+G17+G18 -> -8750 | H19: =H16+H17+H18 -> -8750 | I19: =I16+I17+I18 -> -8750 | J19: =J16+J17+J18 -> -8750 | ... AI19: =AI16+AI17+AI18 -> -16250 | AJ19: =SUM(C19:N19) -> -284000 | AK19: =SUM(O19:Z19) -> 227500 | AL19: =SUM(AA19:AI19) -> -146250
A20: Net change in cash | B20: net_change | C20: =C13+C15+C19 -> -26279.68 | D20: =D13+D15+D19 -> -21300.73 | E20: =E13+E15+E19 -> 87690.98 | F20: =F13+F15+F19 -> 155062.31 | G20: =G13+G15+G19 -> 173946.79 | H20: =H13+H15+H19 -> 89385.3 | I20: =I13+I15+I19 -> -62243.67 | J20: =J13+J15+J19 -> -77242.71 | ... AI20: =AI13+AI15+AI19 -> 89866.5 | AJ20: =SUM(C20:N20) -> 426954.72 | AK20: =SUM(O20:Z20) -> -203558.35 | AL20: =SUM(AA20:AI20) -> 746837.63
A21: Opening cash | B21: open_cash | C21: 420000 | D21: =C22 -> 393720.32 | E21: =D22 -> 372419.59 | F21: =E22 -> 460110.57 | G21: =F22 -> 615172.88 | H21: =G22 -> 789119.67 | I21: =H22 -> 878504.97 | J21: =I22 -> 816261.3 | K21: =J22 -> 739018.59 | ... AI21: =AH22 -> 1300367.5 | AJ21: =C21 -> 420000 | AK21: =O21 -> 846954.72 | AL21: =AA21 -> 643396.37
A22: Ending cash balance | B22: close_cash | C22: =C21+C20 -> 393720.32 | D22: =D21+D20 -> 372419.59 | E22: =E21+E20 -> 460110.57 | F22: =F21+F20 -> 615172.88 | G22: =G21+G20 -> 789119.67 | H22: =H21+H20 -> 878504.97 | I22: =I21+I20 -> 816261.3 | J22: =J21+J20 -> 739018.59 | ... AI22: =AI21+AI20 -> 1390234 | AJ22: =N22 -> 846954.72 | AK22: =Z22 -> 643396.37 | AL22: =AI22 -> 1390234
A23: Cash per balance sheet | B23: bs_cash | C23: =Hist_BS!C6 -> 393720.32 | D23: =Hist_BS!D6 -> 372419.59 | E23: =Hist_BS!E6 -> 460110.57 | F23: =Hist_BS!F6 -> 615172.88 | G23: =Hist_BS!G6 -> 789119.67 | H23: =Hist_BS!H6 -> 878504.97 | I23: =Hist_BS!I6 -> 816261.3 | J23: =Hist_BS!J6 -> 739018.59 | ... AI23: =Hist_BS!AI6 -> 1390234 | AJ23: =N23 -> 846954.72 | AK23: =Z23 -> 643396.37 | AL23: =AI23 -> 1390234
A24: Check: ending cash - balance-sheet cash | B24: check | C24: =ROUND(C22-C23,2) -> 0 | D24: =ROUND(D22-D23,2) -> 0 | E24: =ROUND(E22-E23,2) -> 0 | F24: =ROUND(F22-F23,2) -> 0 | G24: =ROUND(G22-G23,2) -> 0 | H24: =ROUND(H22-H23,2) -> 0 | I24: =ROUND(I22-I23,2) -> 0 | J24: =ROUND(J22-J23,2) -> 0 | ... AI24: =ROUND(AI22-AI23,2) -> 0 | AJ24: =N24 -> 0 | AK24: =Z24 -> 0 | AL24: =AI24 -> 0

Sheet Hist_Balances
A1: ⚠ SIMULATED FINANCIAL INFORMATION - synthetic demonstration accounts of a fictional auto care group, not actual company records. Synthetic data generated for a VisiVault Analytics proof of concept (seed 20240103). Fictional auto care group.
A2: Month-end account balances from the general ledger (debit +, credit -)
A3: Post-closing at year ends. Each column must sum to zero (trial balance).
A5: Account | B5: Name | C5: 2023-12 | D5: 2024-01 | E5: 2024-02 | F5: 2024-03 | G5: 2024-04 | H5: 2024-05 | I5: 2024-06 | J5: 2024-07 | K5: 2024-08 | L5: 2024-09 | M5: 2024-10 | N5: 2024-11 | O5: 2024-12 | P5: 2025-01 | Q5: 2025-02 | R5: 2025-03 | S5: 2025-04 | T5: 2025-05 | U5: 2025-06 | V5: 2025-07 | W5: 2025-08 | X5: 2025-09 | Y5: 2025-10 | Z5: 2025-11 | AA5: 2025-12 | AB5: 2026-01 | AC5: 2026-02 | AD5: 2026-03 | AE5: 2026-04 | AF5: 2026-05 | AG5: 2026-06 | AH5: 2026-07 | AI5: 2026-08 | AJ5: 2026-09
A6: 1000 | B6: Cash - operating account | C6: 420000 | D6: 393720.32 | E6: 372419.59 | F6: 460110.57 | G6: 615172.88 | H6: 789119.67 | I6: 878504.97 | J6: 816261.3 | K6: 739018.59 | L6: 540268.22 | M6: 903226.19 | N6: 1083658.8 | O6: 846954.72 | P6: 691324.08 | Q6: 729463.65 | R6: 772353.79 | S6: 602823.51 | T6: 661000.43 | U6: 628697.79 | V6: 433184.42 | W6: 517582.44 | X6: 493927.6 | Y6: 683095.21 | Z6: 864574.46 | AA6: 643396.37 | AB6: 510492.61 | AC6: 633407.78 | AD6: 930312.83 | AE6: 1079663.6 | AF6: 1191103.8 | AG6: 1342769.4 | AH6: 1129346 | AI6: 1300367.5 | AJ6: 1390234
A7: 1100 | B7: Card & debit processor receivable | C7: 3194.57 | D7: 43915.96 | E7: 23916.32 | F7: 3231.93 | G7: 32226.05 | H7: 28170.23 | I7: 2922.87 | J7: 19522.1 | K7: 12791.81 | L7: 12065.48 | M7: 20038.54 | N7: 19609.27 | O7: 14747.24 | P7: 22357.5 | Q7: 41579.5 | R7: 14466.09 | S7: 28474.78 | T7: 18904.91 | U7: 19040.42 | V7: 41463.18 | W7: 2913.11 | X7: 36090.41 | Y7: 37706.34 | Z7: 6949.82 | AA7: 13180.93 | AB7: 15871.03 | AC7: 15710.83 | AD7: 35867.18 | AE7: 57971.42 | AF7: 6513 | AG7: 35159.21 | AH7: 33836.79 | AI7: 23457.45 | AJ7: 57024.67
A8: 1110 | B8: Insurer receivables (direct billing) | C8: 490451.26 | D8: 433861.48 | E8: 603581.3 | F8: 505108.03 | G8: 496841.21 | H8: 504740 | I8: 344074.43 | J8: 271127.44 | K8: 358310.92 | L8: 622300.62 | M8: 417249.48 | N8: 428467.66 | O8: 363070.71 | P8: 519555.24 | Q8: 579289.91 | R8: 590551.85 | S8: 411207.64 | T8: 501139.62 | U8: 410705.57 | V8: 547488.23 | W8: 616272.2 | X8: 633976.19 | Y8: 585491.41 | Z8: 502017.27 | AA8: 515688.02 | AB8: 830843.66 | AC8: 720229.64 | AD8: 545393.95 | AE8: 623573.87 | AF8: 532091.1 | AG8: 468813.23 | AH8: 661457.7 | AI8: 647790.93 | AJ8: 573560.54
A9: 1120 | B9: Fleet & commercial account receivables | C9: 32873.39 | D9: 32900.14 | E9: 29309.36 | F9: 32521.53 | G9: 44543.71 | H9: 42862.78 | I9: 27303.56 | J9: 42169.94 | K9: 49437.83 | L9: 19809.35 | M9: 42077.21 | N9: 48209.5 | O9: 36457.43 | P9: 39418.16 | Q9: 30312.5 | R9: 39864.83 | S9: 28555.61 | T9: 36881.84 | U9: 22851.74 | V9: 43564.28 | W9: 50096.74 | X9: 38364.26 | Y9: 59712.82 | Z9: 67143.73 | AA9: 33731.06 | AB9: 54150.61 | AC9: 64048.5 | AD9: 68655.47 | AE9: 65040.83 | AF9: 72860.03 | AG9: 55342.77 | AH9: 47783.2 | AI9: 41631.27 | AJ9: 53108.15
A10: 1200 | B10: Parts inventory - stocked | C10: 47419.06 | D10: 45026.45 | E10: 43992.91 | F10: 46568.05 | G10: 33742.94 | H10: 40982.67 | I10: 45501.75 | J10: 45358.58 | K10: 45007.68 | L10: 43061.37 | M10: 41166.38 | N10: 45357.37 | O10: 46654.42 | P10: 45361.44 | Q10: 48026.26 | R10: 46823.72 | S10: 39752.62 | T10: 63987.11 | U10: 64076.25 | V10: 59968.76 | W10: 67045.6 | X10: 66610.3 | Y10: 51836.89 | Z10: 55946.35 | AA10: 70128.9 | AB10: 63867.84 | AC10: 65406.11 | AD10: 62730.29 | AE10: 56051.64 | AF10: 56058.69 | AG10: 61856.32 | AH10: 63125.52 | AI10: 68943.76 | AJ10: 61247.14
A11: 1210 | B11: Special-order parts received for open jobs | C11: 84837.2 | D11: 86686.08 | E11: 52809.7 | F11: 72559.63 | G11: 40181.77 | H11: 36676.56 | I11: 34960.93 | J11: 40863.94 | K11: 111834.28 | L11: 49956.78 | M11: 43051.52 | N11: 78153.71 | O11: 86056.63 | P11: 63033.84 | Q11: 41651.38 | R11: 48103.04 | S11: 73914.72 | T11: 47958.24 | U11: 49604.57 | V11: 58473.01 | W11: 60216.92 | X11: 36790.02 | Y11: 83631.62 | Z11: 108780.73 | AA11: 183079.12 | AB11: 95691.95 | AC11: 78234.82 | AD11: 68474.35 | AE11: 57089.29 | AF11: 53166.16 | AG11: 90227.42 | AH11: 63691.29 | AI11: 61147.68 | AJ11: 65151.63
A12: 1220 | B12: Paint, refinish & detailing materials | C12: 11507.4 | D12: 9219.79 | E12: 9814.85 | F12: 9117.25 | G12: 9516.73 | H12: 9222.49 | I12: 5586.78 | J12: 8171.94 | K12: 3839.27 | L12: 14243.84 | M12: 5223.29 | N12: 6409.11 | O12: 13477.03 | P12: 8975.83 | Q12: 9892.63 | R12: 12972.28 | S12: 6493.03 | T12: 9445.3 | U12: 14425.66 | V12: 7039.89 | W12: 10552.93 | X12: 12471.51 | Y12: 6874.1 | Z12: 6840.3 | AA12: 19198.39 | AB12: 13289.17 | AC12: 13361.61 | AD12: 16296.93 | AE12: 16053.93 | AF12: 7849.79 | AG12: 14236.71 | AH12: 10889.36 | AI12: 18852.56 | AJ12: 11736.47
A13: 1250 | B13: Work in progress - unbilled repair jobs (at cost) | C13: 57150.99 | D13: 145139.37 | E13: 125934.67 | F13: 101396.83 | G13: 150033.5 | H13: 69436.59 | I13: 48288.58 | J13: 64596.25 | K13: 125518.22 | L13: 119095.45 | M13: 108777.83 | N13: 107786.61 | O13: 115167.66 | P13: 87527.68 | Q13: 113290.25 | R13: 84190.62 | S13: 134003.79 | T13: 110064.14 | U13: 123413.89 | V13: 171056.65 | W13: 105185.77 | X13: 115310.77 | Y13: 85917.28 | Z13: 171006.61 | AA13: 215178.21 | AB13: 162719.57 | AC13: 132913.06 | AD13: 113978.6 | AE13: 138398.07 | AF13: 107857.56 | AG13: 91617.59 | AH13: 149798.85 | AI13: 131430.98 | AJ13: 115918.75
A14: 1300 | B14: Prepaid expenses | C14: 0 | D14: 81400 | E14: 74000 | F14: 66600 | G14: 59200 | H14: 51800 | I14: 44400 | J14: 37000 | K14: 29600 | L14: 22200 | M14: 14800 | N14: 7400 | O14: 0 | P14: 92988.4 | Q14: 85366.4 | R14: 77744.4 | S14: 70122.4 | T14: 61357.1 | U14: 52591.8 | V14: 43826.5 | W14: 35061.2 | X14: 26295.9 | Y14: 17530.6 | Z14: 8765.3 | AA14: 0 | AB14: 99310.86 | AC14: 90282.6 | AD14: 81254.34 | AE14: 72226.08 | AF14: 63197.82 | AG14: 54169.56 | AH14: 45141.3 | AI14: 36113.04 | AJ14: 27084.78
A15: 1400 | B15: GST input tax credits | C15: 0 | D15: 26151.17 | E15: 48759.11 | F15: 71828.31 | G15: 26663.98 | H15: 50778.36 | I15: 68774.93 | J15: 18920.92 | K15: 43635.64 | L15: 68743.52 | M15: 25097.51 | N15: 53880.7 | O15: 76908 | P15: 22879.52 | Q15: 48609 | R15: 94618.84 | S15: 41904.93 | T15: 73952.78 | U15: 100647.71 | V15: 29410.17 | W15: 58020.1 | X15: 84166.8 | Y15: 32192.82 | Z15: 69410.91 | AA15: 105752.71 | AB15: 33114.5 | AC15: 65227.72 | AD15: 95466.87 | AE15: 35657.83 | AF15: 72372.25 | AG15: 104133.11 | AH15: 30633.78 | AI15: 62300.34 | AJ15: 91131.52
A16: 1500 | B16: Leasehold improvements | C16: 880000 | D16: 880000 | E16: 880000 | F16: 880000 | G16: 880000 | H16: 880000 | I16: 880000 | J16: 880000 | K16: 880000 | L16: 880000 | M16: 880000 | N16: 880000 | O16: 880000 | P16: 880000 | Q16: 880000 | R16: 1290000 | S16: 1290000 | T16: 1290000 | U16: 1290000 | V16: 1290000 | W16: 1290000 | X16: 1290000 | Y16: 1290000 | Z16: 1290000 | AA16: 1290000 | AB16: 1290000 | AC16: 1290000 | AD16: 1290000 | AE16: 1290000 | AF16: 1290000 | AG16: 1290000 | AH16: 1290000 | AI16: 1290000 | AJ16: 1290000
A17: 1510 | B17: Shop equipment (paint booths, frame machines, lifts) | C17: 995000 | D17: 995000 | E17: 995000 | F17: 995000 | G17: 995000 | H17: 995000 | I17: 995000 | J17: 995000 | K17: 995000 | L17: 995000 | M17: 995000 | N17: 995000 | O17: 995000 | P17: 995000 | Q17: 995000 | R17: 995000 | S17: 1180000 | T17: 1180000 | U17: 1180000 | V17: 1180000 | W17: 1180000 | X17: 1180000 | Y17: 1180000 | Z17: 1180000 | AA17: 1180000 | AB17: 1180000 | AC17: 1222000 | AD17: 1222000 | AE17: 1222000 | AF17: 1317000 | AG17: 1317000 | AH17: 1317000 | AI17: 1317000 | AJ17: 1317000
... A63: 8000 | B63: Income tax expense | C63: 0 | D63: 37.5 | E63: 10327.36 | F63: 13492.24 | G63: 25392.8 | H63: 39528.33 | I63: 35519.03 | J63: 28505.11 | K63: 27509.21 | L63: 34835.3 | M63: 46051.33 | N63: 62574.82 | O63: 0 | P63: 7111.58 | Q63: 11044.09 | R63: 15189 | S63: 7096.75 | T63: 8469.91 | U63: 1759.47 | V63: 0 | W63: 4784.26 | X63: 5039.2 | Y63: 13708.11 | Z63: 18526.95 | AA63: 0 | AB63: 20304.98 | AC63: 24734.66 | AD63: 33959.32 | AE63: 54869.25 | AF63: 77531.86 | AG63: 91775.97 | AH63: 105057.26 | AI63: 122583.22 | AJ63: 134250.03
B64: Check: sum of balances (must be 0) | C64: =ROUND(SUM(C6:C63),2) -> 0 | D64: =ROUND(SUM(D6:D63),2) -> 0 | E64: =ROUND(SUM(E6:E63),2) -> 0 | F64: =ROUND(SUM(F6:F63),2) -> 0 | G64: =ROUND(SUM(G6:G63),2) -> 0 | H64: =ROUND(SUM(H6:H63),2) -> 0 | I64: =ROUND(SUM(I6:I63),2) -> 0 | J64: =ROUND(SUM(J6:J63),2) -> 0 | ... AJ64: =ROUND(SUM(AJ6:AJ63),2) -> 0
